Workbook

Sheet How to use
A1: Opencast Pit Planning & Economics Study — advanced workbook
A2: Built so you can see exactly how every number is calculated. Change the yellow cells and everything else recalculates.
A4: IMPORTANT — about the numbers
A5: All values here are made-up SAMPLE values chosen for demonstration (typical ranges, not data from any real mine). Replace them with figures from your textbook problem, published reports or your own measurements. Do not use confidential mine data without permission. Add this project to your resume only after you can explain every sheet.
A7: What question does each sheet answer?
A8: • Inputs — all assumptions in one place: block size, densities, machine specs, costs, coal price, and the settings for the advanced sheets.
A9: • Reserve — how much coal and overburden is in the pit, and which blocks are worth mining (block / borehole-grid method).
A10: • Geostatistics — how continuous the seam is (semivariogram) and the kriged thickness, with a 95 % confidence interval, at any point.
A11: • Pit design — bench and overall slope geometry, the extra wall rock (slope wedge) added to the stripping ratio, and the planar-failure factor of safety.
A12: • Fleet — how many excavators and dumpers are needed to reach the production target.
A13: • Safety — blast ground vibration against DGMS limits, and the stopping distance of a loaded dumper on the ramp.
A14: • Quality and royalty — washability (float-and-sink) yield, whether washing pays, and the statutory levies: royalty, DMF and NMET.
... A54: Royalty on coal is 14 % ad valorem (MMDR Act 1957, Second Schedule; GSR 349(E) of 10 May 2012). DMF is 30 % of royalty for leases granted before 12 January 2015 and 10 % after. NMET at 2 % and the other-levy figure are placeholders to verify. Permissible PPV values are from DGMS (Tech)(S&T) Circular No. 7 of 1997. Check current notifications before relying on any of them.

Sheet Inputs
A1: Inputs — every assumption in one place
A2: SAMPLE VALUES chosen by Claude for demonstration (typical ranges, not from any real mine). Replace the yellow cells with your textbook / published data. Sections 6 to 12 drive the advanced sheets.
A4: Parameter | B4: Value | C4: Unit | D4: What it means / typical range
A5: 1. Block model and production target
A6: Block length | B6: 100 | C6: m | D6: Each block is the area of influence of one borehole (grid spacing).
A7: Block width | B7: 100 | C7: m | D7: Same idea, other direction. Block area = length × width.
A8: Coal relative density | B8: 1.4 | C8: t/m³ | D8: Typical Indian non-coking coal about 1.3 to 1.6.
A9: Overburden density in the bank | B9: 2.2 | C9: t/BCM | D9: BCM = bank cubic metre (rock measured before blasting). Sandstone/shale mix about 2.0 to 2.5.
A10: Mining recovery | B10: 0.92 | C10: fraction | D10: Share of coal in place that is actually produced (losses at roof, floor, edges). Typical 0.90 to 0.95.
A11: Annual coal production target | B11: 500000 | C11: t/year | D11: Target the fleet must achieve each year.
A12: 2. Excavator
A13: Bucket capacity | B13: 4 | C13: m³ (heaped) | D13: Rated bucket size of the hydraulic excavator.
A14: Bucket fill factor | B14: 0.85 | C14: fraction | D14: How full the bucket really is. Typical 0.75 to 0.95.
A15: Swell factor, overburden | B15: 1.35 | C15: loose ÷ bank | D15: Blasted rock occupies more volume than in the bank. Typical 1.25 to 1.50.
A16: Swell factor, coal | B16: 1.3 | C16: loose ÷ bank | D16: Typical 1.20 to 1.40.
A17: Excavator cycle time | B17: 30 | C17: seconds | D17: Dig, swing, dump, return for one bucket. Typical 25 to 35 s.
A18: Excavator job efficiency | B18: 50 | C18: min per hour | D18: Productive minutes in each hour after small delays. Typical 45 to 55.
A19: 3. Dumpers and haul route
A20: Dumper rated payload | B20: 35 | C20: t | D20: Maximum load per trip.
A21: Haul distance, overburden to dump | B21: 2 | C21: km one way | D21: Distance from pit face to external or internal dump.
A22: Haul distance, coal to stockyard | B22: 3 | C22: km one way | D22: Distance from pit face to coal stockyard.
A23: Average loaded speed | B23: 20 | C23: km/h | D23: Slower than empty because of ramp gradient and rolling resistance.
A24: Average empty speed | B24: 28 | C24: km/h | D24: Returning empty.
A25: Spotting time at excavator | B25: 0.7 | C25: min | D25: Dumper positions itself under the bucket.
A26: Dumping and manoeuvring time | B26: 1.3 | C26: min | D26: Reverse, tip, pull away.
A27: Dumper job efficiency | B27: 50 | C27: min per hour | D27: Productive minutes in each hour.
A28: 4. Working time
A29: Working days per year | B29: 330 | C29: days | D29: Calendar days minus holidays and monsoon stoppages.
A30: Shifts per day | B30: 3 | C30: shifts
A31: Hours per shift | B31: 8 | C31: hours
A32: Machine availability | B32: 0.85 | C32: fraction | D32: Share of time the machine is mechanically ready.
A33: Machine utilisation | B33: 0.8 | C33: fraction | D33: Share of available time the machine is actually working.
A34: 5. Costs, price and capital
A35: Drilling and blasting, overburden | B35: 35 | C35: ₹/BCM | D35: Link this to your Blast Design Calculator cost estimate later.
A36: Drilling and blasting, coal | B36: 20 | C36: ₹/t
A37: Excavator hourly cost | B37: 4500 | C37: ₹/hour | D37: Ownership + fuel + operator + maintenance, for one hour.
A38: Dumper hourly cost | B38: 3000 | C38: ₹/hour | D38: Same idea for one dumper.
A39: Coal handling and dispatch | B39: 150 | C39: ₹/t | D39: Crushing, loading to trucks or rail, weighing.
A40: Overheads and other site costs | B40: 600 | C40: ₹/t | D40: Supervision, dewatering, power, admin, safety.
A41: Royalty and statutory levies | B41: 900 | C41: ₹/t | D41: Check the current statutory rates; this is only a placeholder.
A42: Coal selling price | B42: 2200 | C42: ₹/t | D42: Price at the mine. Placeholder, vary it to see the effect.
A43: Non-equipment capital cost | B43: 10 | C43: ₹ crore | D43: Land, haul roads, infrastructure, clearances. Equipment ownership is already inside the hourly costs above, so it is not repeated here.
A44: Discount rate | B44: 0.1 | C44: fraction | D44: Used to bring future profits to today's value.
A45: 6. Model switches (advanced modules)
A46: Include pit-slope wedge in stripping ratio | B46: 1 | C46: 1 = yes, 0 = no | D46: Adds the extra overburden removed to form stable pit walls (Pit design sheet). 0 gives the simple block-only stripping ratio.
A47: Use statutory royalty build-up | B47: 0 | C47: 1 = yes, 0 = flat | D47: 1 = royalty + DMF + NMET + other levies from the Quality and royalty sheet (about ₹417/t at the sample price, well below the ₹900/t placeholder, so turning it on makes every block economic). 0 = the flat ₹/t placeholder in section 5.
A48: Sell washed coal instead of raw ROM coal | B48: 0 | C48: 1 = washed, 0 = raw | D48: 1 = revenue per tonne of ROM feed after washing (yield × washed price − washing cost). 0 = raw coal at the selling price in section 5.
A49: 7. Geostatistics: variogram and kriging
A50: Remove linear trend before kriging | B50: 1 | C50: 1 = yes, 0 = no | D50: Seam thickness often trends across a deposit. Kriging the residuals avoids a variogram that never levels off.
A51: Variogram model | B51: 1 | C51: 1, 2 or 3 | D51: 1 = spherical, 2 = exponential, 3 = Gaussian. Gaussian needs a nugget above zero to stay numerically stable.
A52: Nugget, c0 | B52: 0.08 | C52: m² | D52: Variance at very short distance (sampling error plus micro-scale variation). Fit by eye against the Geostatistics chart, or use Solver.
A53: Partial sill, c | B53: 0.07 | C53: m² | D53: Spatially correlated variance. Total sill = nugget + partial sill.
A54: Range, a | B54: 200 | C54: m | D54: Distance beyond which boreholes are no longer correlated (practical range for exponential and Gaussian).
A55: Lag class width | B55: 100 | C55: m | D55: Distance bin for the experimental variogram. Usually the borehole spacing.
A56: Kriging target, X | B56: 200 | C56: m | D56: East-west position from the grid origin. Block centres are at (column number − 0.5) × block length.
A57: Kriging target, Y | B57: 200 | C57: m | D57: North-south position. Block centres are at (row letter − 0.5) × block width, with A = 1.
A58: 8. Pit design and slope stability
A59: Bench height | B59: 10 | C59: m | D59: Typical 6 to 15 m for hydraulic excavators; roughly the excavator's digging height.
A60: Bench face angle | B60: 70 | C60: degrees | D60: Slope of one bench face. Typical 60 to 80 degrees in overburden.
A61: Berm (catch bench) width | B61: 8 | C61: m | D61: Width of the flat step left between benches to catch falling rock.
A62: Rock mass cohesion | B62: 30 | C62: kPa | D62: Shear strength at zero normal stress. Take from lab or published rock-mass data.
A63: Friction angle | B63: 30 | C63: degrees | D63: Angle of internal friction of the failure plane. Typical 25 to 40 degrees.
A64: Failure plane dip | B64: 35 | C64: degrees | D64: Dip of the planar surface a wedge could slide on (bedding or a joint set). Must be flatter than the pit slope for failure to be possible.
A65: Target factor of safety | B65: 1.3 | C65: ratio | D65: Typical 1.2 to 1.5 depending on how long the slope must stand and the consequence of failure.
A66: Haul ramp gradient | B66: 8 | C66: % | D66: Rise per 100 m of ramp. 8 % is about 1 in 12.5. Also used for stopping distance on the Safety sheet.
A67: 9. Mine planning
A68: Taylor's rule constant | B68: 0.2 | C68: years | D68: Taylor (1977): life ≈ 0.2 × (reserve in tonnes)^0.25. Empirical, from metal mines; accuracy about ±25 %.
A69: Taylor's rule exponent | B69: 0.25 | C69: power | D69: Exponent on the reserve tonnage.
A70: 10. Washability and statutory levies
A71: Target clean-coal ash | B71: 28 | C71: % | D71: Ash the washed product must meet. Float-and-sink data are on the Quality and royalty sheet.
A72: Washery organic efficiency | B72: 0.94 | C72: fraction | D72: Actual yield ÷ theoretical yield at the same ash. Typical 0.90 to 0.97.
A73: Washed coal selling price | B73: 4200 | C73: ₹/t | D73: Price of the washed product. Placeholder: vary it to find the break-even washed price.
A74: Washing cost | B74: 150 | C74: ₹/t of feed | D74: Operating cost of the washery per tonne of ROM coal fed.
A75: Reject value | B75: 0 | C75: ₹/t of reject | D75: Sale value of rejects (middlings, shale). Often near zero.
A76: Royalty rate on coal | B76: 0.14 | C76: of coal price | D76: 14 % ad valorem (MMDR Act 1957, Second Schedule; GSR 349(E) of 10 May 2012). Verify the current notification.
A77: DMF contribution | B77: 0.3 | C77: of royalty | D77: 30 % of royalty for leases granted before 12 Jan 2015; 10 % for leases granted on or after that date.
A78: NMET contribution | B78: 0.03 | C78: of royalty | D78: National Mineral Exploration Trust, 3 % of royalty under the MMDR Act. Verify before relying on it.
A79: Other statutory levies | B79: 10 | C79: ₹/t | D79: Placeholder for stowing excise duty, environment and similar per-tonne levies. Check current notifications.
A80: 11. Equipment capital, depreciation and tax
A81: Excavator purchase price | B81: 4 | C81: ₹ crore each | D81: Sample price for a 4 m³ hydraulic excavator. Replace with a quotation.
A82: Dumper purchase price | B82: 2 | C82: ₹ crore each | D82: Sample price for a 35 t rear-dump truck.
A83: Ownership share of machine hourly cost | B83: 0.25 | C83: fraction | D83: Part of the hourly cost that is ownership (depreciation and interest). It is removed from cash cost on the Finance sheet because capital and depreciation are modelled explicitly there.
A84: Depreciation method | B84: 1 | C84: 1, 2 or 3 | D84: 1 = straight line, 2 = written-down value (declining balance), 3 = units of production.
A85: Depreciable life of equipment | B85: 8 | C85: years | D85: Used by the straight-line method.
A86: Written-down value rate | B86: 0.2 | C86: per year | D86: Used by method 2. Check the rate that applies to your equipment class.
A87: Value realised at closure | B87: 0.5 | C87: of book value | D87: Share of the remaining book value recovered by selling equipment when the mine closes. The shortfall is a tax-deductible loss.
A88: Income tax rate | B88: 0.25 | C88: of taxable profit | D88: Placeholder. Use the current corporate rate including surcharge and cess that applies to your case.
A89: 12. Blasting, vibration and haul-road safety
A90: Powder factor | B90: 0.35 | C90: kg/m³ | D90: Explosive per bank cubic metre of overburden. Typical 0.3 to 0.6.
A91: Explosive cost | B91: 55 | C91: ₹/kg | D91: Delivered cost of bulk explosive. Placeholder.
A92: Blast burden | B92: 4 | C92: m | D92: Distance from a hole to the free face.
A93: Blast hole spacing | B93: 5 | C93: m | D93: Distance between holes in a row.
A94: Holes firing per delay | B94: 2 | C94: holes | D94: Holes that fire at the same instant. Maximum charge per delay controls ground vibration.
A95: Distance to nearest structure | B95: 300 | C95: m | D95: Nearest house, building or sensitive structure not owned by the mine.
A96: Site constant K (vibration) | B96: 500 | C96: mm/s | D96: From the scaled-distance law PPV = K × (R/√Q)^−β. Found by regression on blast monitoring data at your site.
A97: Site constant β (vibration) | B97: 1.6 | C97: power | D97: Attenuation exponent. Typical 1.2 to 2.0.
A98: Structure category | B98: 1 | C98: 1 to 5 | D98: Row of the DGMS table on the Safety sheet. 1 = domestic houses not owned by the mine.
A99: Dominant frequency band | B99: 2 | C99: 1, 2 or 3 | D99: 1 = below 8 Hz, 2 = 8 to 25 Hz, 3 = above 25 Hz.
A100: Driver reaction time | B100: 1.5 | C100: s | D100: Time before the brakes are applied. Typical 1.0 to 2.0 s.
A101: Braking friction coefficient | B101: 0.35 | C101: ratio | D101: Tyre-to-road friction available for braking. Lower on wet or loose surfaces.
...

Sheet Reserve
A1: Reserve — how much coal and overburden, and which blocks are worth mining?
A2: Block (borehole-grid) method: each borehole represents one block. Enter thickness from each borehole; everything else is formula. SAMPLE DATA.
A5: Block | B5: Overburden thickness (m) | C5: Coal seam thickness (m) | D5: Block area (m²) | E5: Overburden volume (BCM) | F5: Coal volume (m³) | G5: Coal in place (t) | H5: Stripping ratio (m³/t) | I5: Economic to mine? (SR ≤ break-even)
A6: A1 | B6: 18 | C6: 8.5 | D6: =Inputs!$B$6*Inputs!$B$7 -> 10000 | E6: =D6*B6 -> 180000 | F6: =D6*C6 -> 85000 | G6: =F6*Inputs!$B$8 -> 119000 | H6: =IFERROR(E6/G6,0) -> 1.512605 | I6: =IF(H6<=Economics!$B$21,"Yes","No") -> Yes
A7: A2 | B7: 23 | C7: 8 | D7: =Inputs!$B$6*Inputs!$B$7 -> 10000 | E7: =D7*B7 -> 230000 | F7: =D7*C7 -> 80000 | G7: =F7*Inputs!$B$8 -> 112000 | H7: =IFERROR(E7/G7,0) -> 2.0535714 | I7: =IF(H7<=Economics!$B$21,"Yes","No") -> Yes
A8: A3 | B8: 29 | C8: 7.5 | D8: =Inputs!$B$6*Inputs!$B$7 -> 10000 | E8: =D8*B8 -> 290000 | F8: =D8*C8 -> 75000 | G8: =F8*Inputs!$B$8 -> 105000 | H8: =IFERROR(E8/G8,0) -> 2.7619048 | I8: =IF(H8<=Economics!$B$21,"Yes","No") -> Yes
A9: A4 | B9: 36 | C9: 7 | D9: =Inputs!$B$6*Inputs!$B$7 -> 10000 | E9: =D9*B9 -> 360000 | F9: =D9*C9 -> 70000 | G9: =F9*Inputs!$B$8 -> 98000 | H9: =IFERROR(E9/G9,0) -> 3.6734694 | I9: =IF(H9<=Economics!$B$21,"Yes","No") -> Yes
A10: A5 | B10: 45 | C10: 6.5 | D10: =Inputs!$B$6*Inputs!$B$7 -> 10000 | E10: =D10*B10 -> 450000 | F10: =D10*C10 -> 65000 | G10: =F10*Inputs!$B$8 -> 91000 | H10: =IFERROR(E10/G10,0) -> 4.9450549 | I10: =IF(H10<=Economics!$B$21,"Yes","No") -> No
A11: B1 | B11: 20 | C11: 9 | D11: =Inputs!$B$6*Inputs!$B$7 -> 10000 | E11: =D11*B11 -> 200000 | F11: =D11*C11 -> 90000 | G11: =F11*Inputs!$B$8 -> 126000 | H11: =IFERROR(E11/G11,0) -> 1.5873016 | I11: =IF(H11<=Economics!$B$21,"Yes","No") -> Yes
A12: B2 | B12: 25 | C12: 8.5 | D12: =Inputs!$B$6*Inputs!$B$7 -> 10000 | E12: =D12*B12 -> 250000 | F12: =D12*C12 -> 85000 | G12: =F12*Inputs!$B$8 -> 119000 | H12: =IFERROR(E12/G12,0) -> 2.1008403 | I12: =IF(H12<=Economics!$B$21,"Yes","No") -> Yes
A13: B3 | B13: 31 | C13: 8 | D13: =Inputs!$B$6*Inputs!$B$7 -> 10000 | E13: =D13*B13 -> 310000 | F13: =D13*C13 -> 80000 | G13: =F13*Inputs!$B$8 -> 112000 | H13: =IFERROR(E13/G13,0) -> 2.7678571 | I13: =IF(H13<=Economics!$B$21,"Yes","No") -> Yes
A14: B4 | B14: 38 | C14: 7.5 | D14: =Inputs!$B$6*Inputs!$B$7 -> 10000 | E14: =D14*B14 -> 380000 | F14: =D14*C14 -> 75000 | G14: =F14*Inputs!$B$8 -> 105000 | H14: =IFERROR(E14/G14,0) -> 3.6190476 | I14: =IF(H14<=Economics!$B$21,"Yes","No") -> Yes
A15: B5 | B15: 47 | C15: 6.5 | D15: =Inputs!$B$6*Inputs!$B$7 -> 10000 | E15: =D15*B15 -> 470000 | F15: =D15*C15 -> 65000 | G15: =F15*Inputs!$B$8 -> 91000 | H15: =IFERROR(E15/G15,0) -> 5.1648352 | I15: =IF(H15<=Economics!$B$21,"Yes","No") -> No
A16: C1 | B16: 19 | C16: 9.5 | D16: =Inputs!$B$6*Inputs!$B$7 -> 10000 | E16: =D16*B16 -> 190000 | F16: =D16*C16 -> 95000 | G16: =F16*Inputs!$B$8 -> 133000 | H16: =IFERROR(E16/G16,0) -> 1.4285714 | I16: =IF(H16<=Economics!$B$21,"Yes","No") -> Yes
A17: C2 | B17: 24 | C17: 9 | D17: =Inputs!$B$6*Inputs!$B$7 -> 10000 | E17: =D17*B17 -> 240000 | F17: =D17*C17 -> 90000 | G17: =F17*Inputs!$B$8 -> 126000 | H17: =IFERROR(E17/G17,0) -> 1.9047619 | I17: =IF(H17<=Economics!$B$21,"Yes","No") -> Yes
... A25: D5 | B25: 43 | C25: 6 | D25: =Inputs!$B$6*Inputs!$B$7 -> 10000 | E25: =D25*B25 -> 430000 | F25: =D25*C25 -> 60000 | G25: =F25*Inputs!$B$8 -> 84000 | H25: =IFERROR(E25/G25,0) -> 5.1190476 | I25: =IF(H25<=Economics!$B$21,"Yes","No") -> No
A26: Total / overall | B26: =AVERAGE(B6:B25) -> 30.55 | C26: =AVERAGE(C6:C25) -> 7.875 | D26: =SUM(D6:D25) -> 200000 | E26: =SUM(E6:E25) -> 6110000 | F26: =SUM(F6:F25) -> 1575000 | G26: =SUM(G6:G25) -> 2205000 | H26: =IFERROR(E26/G26,0) -> 2.7709751 | I26: =COUNTIF(I6:I25,"Yes")&" of "&COUNTA(A6:A25)&" blocks" -> 16 of 20 blocks
A27: Row 26: thickness columns show the average; other columns show totals. Overall stripping ratio = total overburden ÷ total coal.
A28: All blocks
A29: Coal in place | B29: =G26 -> 2205000 | C29: t | D29: Sum of all block tonnages.
A30: Recoverable coal | B30: =B29*Inputs!$B$10 -> 2028600 | C30: t | D30: Coal in place × mining recovery.
A31: Overall stripping ratio | B31: =H26 -> 2.7709751 | C31: m³/t | D31: Total overburden ÷ total coal in place.
A32: Mine life, all blocks | B32: =B30/Inputs!$B$11 -> 4.0572 | C32: years | D32: Recoverable coal ÷ annual production.
A33: Economic blocks only (stripping ratio at or below the break-even)
A34: Mining a block above the break-even loses money, so the plan keeps only the 'Yes' blocks. This is the idea behind a pit limit.
A35: Number of economic blocks | B35: =COUNTIF(I6:I25,"Yes") -> 16 | C35: blocks | D35: Blocks marked Yes.
A36: Coal in place, economic blocks | B36: =SUMIF(I6:I25,"Yes",G6:G25) -> 1841000 | C36: t | D36: SUMIF over the Yes blocks.
A37: Overburden, economic blocks | B37: =SUMIF(I6:I25,"Yes",E6:E25) -> 4320000 | C37: BCM | D37: SUMIF over the Yes blocks.
A38: Stripping ratio, economic blocks | B38: ='Pit design'!$B$37 -> 2.9310858 | C38: m³/t | D38: Includes the pit-slope wedge when the switch on Inputs is 1 (Pit design sheet). Used by the Fleet and Economics sheets.
A39: Recoverable coal, economic blocks | B39: =B36*Inputs!$B$10 -> 1693720 | C39: t | D39: Used for mine life and the cash flow.
A40: Mine life, economic blocks | B40: =B39/Inputs!$B$11 -> 3.38744 | C40: years | D40: Recoverable coal ÷ annual production.

Sheet Geostatistics
A1: Geostatistics — how continuous is the seam, and what is the kriged estimate at an unsampled point?
A2: Semivariogram of the borehole thicknesses, a fitted model, and ordinary kriging with a 95 % confidence interval. SAMPLE DATA: replace the boreholes on the Reserve sheet.
A4: A. Borehole data and trend surface
A5: Block | B5: X (m) | C5: Y (m) | D5: Coal seam thickness (m) | E5: Overburden thickness (m) | F5: Coal trend (m) | G5: Coal value used (m) | H5: Overburden trend (m) | I5: Overburden value used (m)
A6: =Reserve!A6 -> A1 | B6: =(VALUE(MID(A6,2,9))-0.5)*Inputs!$B$6 -> 50 | C6: =(CODE(UPPER(LEFT(A6,1)))-65+0.5)*Inputs!$B$7 -> 50 | D6: =Reserve!C6 -> 8.5 | E6: =Reserve!B6 -> 18 | F6: =IF(Inputs!$B$50=1,$B$29+$C$29*B6+$D$29*C6,0) -> 8.935 | G6: =D6-F6 -> -0.435 | H6: =IF(Inputs!$B$50=1,$B$30+$C$30*B6+$D$30*C6,0) -> 18.2 | I6: =E6-H6 -> -0.2
A7: =Reserve!A7 -> A2 | B7: =(VALUE(MID(A7,2,9))-0.5)*Inputs!$B$6 -> 150 | C7: =(CODE(UPPER(LEFT(A7,1)))-65+0.5)*Inputs!$B$7 -> 50 | D7: =Reserve!C7 -> 8 | E7: =Reserve!B7 -> 23 | F7: =IF(Inputs!$B$50=1,$B$29+$C$29*B7+$D$29*C7,0) -> 8.3225 | G7: =D7-F7 -> -0.3225 | H7: =IF(Inputs!$B$50=1,$B$30+$C$30*B7+$D$30*C7,0) -> 24.75 | I7: =E7-H7 -> -1.75
A8: =Reserve!A8 -> A3 | B8: =(VALUE(MID(A8,2,9))-0.5)*Inputs!$B$6 -> 250 | C8: =(CODE(UPPER(LEFT(A8,1)))-65+0.5)*Inputs!$B$7 -> 50 | D8: =Reserve!C8 -> 7.5 | E8: =Reserve!B8 -> 29 | F8: =IF(Inputs!$B$50=1,$B$29+$C$29*B8+$D$29*C8,0) -> 7.71 | G8: =D8-F8 -> -0.21 | H8: =IF(Inputs!$B$50=1,$B$30+$C$30*B8+$D$30*C8,0) -> 31.3 | I8: =E8-H8 -> -2.3
A9: =Reserve!A9 -> A4 | B9: =(VALUE(MID(A9,2,9))-0.5)*Inputs!$B$6 -> 350 | C9: =(CODE(UPPER(LEFT(A9,1)))-65+0.5)*Inputs!$B$7 -> 50 | D9: =Reserve!C9 -> 7 | E9: =Reserve!B9 -> 36 | F9: =IF(Inputs!$B$50=1,$B$29+$C$29*B9+$D$29*C9,0) -> 7.0975 | G9: =D9-F9 -> -0.0975 | H9: =IF(Inputs!$B$50=1,$B$30+$C$30*B9+$D$30*C9,0) -> 37.85 | I9: =E9-H9 -> -1.85
A10: =Reserve!A10 -> A5 | B10: =(VALUE(MID(A10,2,9))-0.5)*Inputs!$B$6 -> 450 | C10: =(CODE(UPPER(LEFT(A10,1)))-65+0.5)*Inputs!$B$7 -> 50 | D10: =Reserve!C10 -> 6.5 | E10: =Reserve!B10 -> 45 | F10: =IF(Inputs!$B$50=1,$B$29+$C$29*B10+$D$29*C10,0) -> 6.485 | G10: =D10-F10 -> 0.015 | H10: =IF(Inputs!$B$50=1,$B$30+$C$30*B10+$D$30*C10,0) -> 44.4 | I10: =E10-H10 -> 0.6
A11: =Reserve!A11 -> B1 | B11: =(VALUE(MID(A11,2,9))-0.5)*Inputs!$B$6 -> 50 | C11: =(CODE(UPPER(LEFT(A11,1)))-65+0.5)*Inputs!$B$7 -> 150 | D11: =Reserve!C11 -> 9 | E11: =Reserve!B11 -> 20 | F11: =IF(Inputs!$B$50=1,$B$29+$C$29*B11+$D$29*C11,0) -> 9.045 | G11: =D11-F11 -> -0.045 | H11: =IF(Inputs!$B$50=1,$B$30+$C$30*B11+$D$30*C11,0) -> 17.7 | I11: =E11-H11 -> 2.3
A12: =Reserve!A12 -> B2 | B12: =(VALUE(MID(A12,2,9))-0.5)*Inputs!$B$6 -> 150 | C12: =(CODE(UPPER(LEFT(A12,1)))-65+0.5)*Inputs!$B$7 -> 150 | D12: =Reserve!C12 -> 8.5 | E12: =Reserve!B12 -> 25 | F12: =IF(Inputs!$B$50=1,$B$29+$C$29*B12+$D$29*C12,0) -> 8.4325 | G12: =D12-F12 -> 0.0675 | H12: =IF(Inputs!$B$50=1,$B$30+$C$30*B12+$D$30*C12,0) -> 24.25 | I12: =E12-H12 -> 0.75
A13: =Reserve!A13 -> B3 | B13: =(VALUE(MID(A13,2,9))-0.5)*Inputs!$B$6 -> 250 | C13: =(CODE(UPPER(LEFT(A13,1)))-65+0.5)*Inputs!$B$7 -> 150 | D13: =Reserve!C13 -> 8 | E13: =Reserve!B13 -> 31 | F13: =IF(Inputs!$B$50=1,$B$29+$C$29*B13+$D$29*C13,0) -> 7.82 | G13: =D13-F13 -> 0.18 | H13: =IF(Inputs!$B$50=1,$B$30+$C$30*B13+$D$30*C13,0) -> 30.8 | I13: =E13-H13 -> 0.2
A14: =Reserve!A14 -> B4 | B14: =(VALUE(MID(A14,2,9))-0.5)*Inputs!$B$6 -> 350 | C14: =(CODE(UPPER(LEFT(A14,1)))-65+0.5)*Inputs!$B$7 -> 150 | D14: =Reserve!C14 -> 7.5 | E14: =Reserve!B14 -> 38 | F14: =IF(Inputs!$B$50=1,$B$29+$C$29*B14+$D$29*C14,0) -> 7.2075 | G14: =D14-F14 -> 0.2925 | H14: =IF(Inputs!$B$50=1,$B$30+$C$30*B14+$D$30*C14,0) -> 37.35 | I14: =E14-H14 -> 0.65
A15: =Reserve!A15 -> B5 | B15: =(VALUE(MID(A15,2,9))-0.5)*Inputs!$B$6 -> 450 | C15: =(CODE(UPPER(LEFT(A15,1)))-65+0.5)*Inputs!$B$7 -> 150 | D15: =Reserve!C15 -> 6.5 | E15: =Reserve!B15 -> 47 | F15: =IF(Inputs!$B$50=1,$B$29+$C$29*B15+$D$29*C15,0) -> 6.595 | G15: =D15-F15 -> -0.095 | H15: =IF(Inputs!$B$50=1,$B$30+$C$30*B15+$D$30*C15,0) -> 43.9 | I15: =E15-H15 -> 3.1
A16: =Reserve!A16 -> C1 | B16: =(VALUE(MID(A16,2,9))-0.5)*Inputs!$B$6 -> 50 | C16: =(CODE(UPPER(LEFT(A16,1)))-65+0.5)*Inputs!$B$7 -> 250 | D16: =Reserve!C16 -> 9.5 | E16: =Reserve!B16 -> 19 | F16: =IF(Inputs!$B$50=1,$B$29+$C$29*B16+$D$29*C16,0) -> 9.155 | G16: =D16-F16 -> 0.345 | H16: =IF(Inputs!$B$50=1,$B$30+$C$30*B16+$D$30*C16,0) -> 17.2 | I16: =E16-H16 -> 1.8
A17: =Reserve!A17 -> C2 | B17: =(VALUE(MID(A17,2,9))-0.5)*Inputs!$B$6 -> 150 | C17: =(CODE(UPPER(LEFT(A17,1)))-65+0.5)*Inputs!$B$7 -> 250 | D17: =Reserve!C17 -> 9 | E17: =Reserve!B17 -> 24 | F17: =IF(Inputs!$B$50=1,$B$29+$C$29*B17+$D$29*C17,0) -> 8.5425 | G17: =D17-F17 -> 0.4575 | H17: =IF(Inputs!$B$50=1,$B$30+$C$30*B17+$D$30*C17,0) -> 23.75 | I17: =E17-H17 -> 0.25
... A25: =Reserve!A25 -> D5 | B25: =(VALUE(MID(A25,2,9))-0.5)*Inputs!$B$6 -> 450 | C25: =(CODE(UPPER(LEFT(A25,1)))-65+0.5)*Inputs!$B$7 -> 350 | D25: =Reserve!C25 -> 6 | E25: =Reserve!B25 -> 43 | F25: =IF(Inputs!$B$50=1,$B$29+$C$29*B25+$D$29*C25,0) -> 6.815 | G25: =D25-F25 -> -0.815 | H25: =IF(Inputs!$B$50=1,$B$30+$C$30*B25+$D$30*C25,0) -> 42.9 | I25: =E25-H25 -> 0.1
A27: Trend surface: thickness = a + b × X + c × Y (least squares). Used only when the trend switch on Inputs is 1.
A28: Quantity | B28: a (intercept, m) | C28: b (m per m, X) | D28: c (m per m, Y) | E28: R²
A29: Coal seam thickness | B29: =INDEX(LINEST($D$6:$D$25,$B$6:$C$25,TRUE(),TRUE()),1,3) -> 9.18625 | C29: =INDEX(LINEST($D$6:$D$25,$B$6:$C$25,TRUE(),TRUE()),1,2) -> -0.006125 | D29: =INDEX(LINEST($D$6:$D$25,$B$6:$C$25,TRUE(),TRUE()),1,1) -> 0.0011 | E29: =INDEX(LINEST($D$6:$D$25,$B$6:$C$25,TRUE(),TRUE()),3,1) -> 0.85344948
A30: Overburden thickness | B30: =INDEX(LINEST($E$6:$E$25,$B$6:$C$25,TRUE(),TRUE()),1,3) -> 15.175 | C30: =INDEX(LINEST($E$6:$E$25,$B$6:$C$25,TRUE(),TRUE()),1,2) -> 0.0655 | D30: =INDEX(LINEST($E$6:$E$25,$B$6:$C$25,TRUE(),TRUE()),1,1) -> -0.005 | E30: =INDEX(LINEST($E$6:$E$25,$B$6:$C$25,TRUE(),TRUE()),3,1) -> 0.97808001
A32: B. Experimental semivariogram and the fitted model
A33: Lag class | B33: Nominal lag (m) | C33: Pairs | D33: Mean distance (m) | E33: Experimental γ (m²) | F33: Model γ (m²) | G33: Weighted squared error | I33: h (m) | J33: Model γ(h)
A34: 1 | B34: =A34*Inputs!$B$55 -> 100 | C34: =COUNTIFS($B$102:$U$121,">="&(B34-Inputs!$B$55/2),$B$102:$U$121,"<"&(B34+Inputs!$B$55/2))/2 -> 55 | D34: =IFERROR(AVERAGEIFS($B$102:$U$121,$B$102:$U$121,">="&(B34-Inputs!$B$55/2),$B$102:$U$121,"<"&(B34+Inputs!$B$55/2)),0) -> 118.07477 | E34: =IFERROR(AVERAGEIFS($B$125:$U$144,$B$102:$U$121,">="&(B34-Inputs!$B$55/2),$B$102:$U$121,"<"&(B34+Inputs!$B$55/2)),0) -> 0.12902864 | F34: =IF(D34=0,0,CHOOSE(Inputs!$B$51,IF(D34>=Inputs!$B$54,Inputs!$B$52+Inputs!$B$53,Inputs!$B$52+Inputs!$B$53*(1.5*D34/Inputs!$B$54-0.5*(D34/Inputs!$B$54)^3)),Inputs!$B$52+Inputs!$B$53*(1-EXP(-3*D34/Inputs!$B$54)),Inputs!$B$52+Inputs!$B$53*(1-EXP(-3*(D34/Inputs!$B$54)^2)))) -> 0.13478732 | G34: =C34*(E34-F34)^2 -> 0.0018239324 | I34: 0 | J34: =IF(I34=0,0,CHOOSE(Inputs!$B$51,IF(I34>=Inputs!$B$54,Inputs!$B$52+Inputs!$B$53,Inputs!$B$52+Inputs!$B$53*(1.5*I34/Inputs!$B$54-0.5*(I34/Inputs!$B$54)^3)),Inputs!$B$52+Inputs!$B$53*(1-EXP(-3*I34/Inputs!$B$54)),Inputs!$B$52+Inputs!$B$53*(1-EXP(-3*(I34/Inputs!$B$54)^2)))) -> 0
A35: 2 | B35: =A35*Inputs!$B$55 -> 200 | C35: =COUNTIFS($B$102:$U$121,">="&(B35-Inputs!$B$55/2),$B$102:$U$121,"<"&(B35+Inputs!$B$55/2))/2 -> 56 | D35: =IFERROR(AVERAGEIFS($B$102:$U$121,$B$102:$U$121,">="&(B35-Inputs!$B$55/2),$B$102:$U$121,"<"&(B35+Inputs!$B$55/2)),0) -> 214.3327 | E35: =IFERROR(AVERAGEIFS($B$125:$U$144,$B$102:$U$121,">="&(B35-Inputs!$B$55/2),$B$102:$U$121,"<"&(B35+Inputs!$B$55/2)),0) -> 0.15881652 | F35: =IF(D35=0,0,CHOOSE(Inputs!$B$51,IF(D35>=Inputs!$B$54,Inputs!$B$52+Inputs!$B$53,Inputs!$B$52+Inputs!$B$53*(1.5*D35/Inputs!$B$54-0.5*(D35/Inputs!$B$54)^3)),Inputs!$B$52+Inputs!$B$53*(1-EXP(-3*D35/Inputs!$B$54)),Inputs!$B$52+Inputs!$B$53*(1-EXP(-3*(D35/Inputs!$B$54)^2)))) -> 0.15 | G35: =C35*(E35-F35)^2 -> 0.0043529353 | I35: 50 | J35: =IF(I35=0,0,CHOOSE(Inputs!$B$51,IF(I35>=Inputs!$B$54,Inputs!$B$52+Inputs!$B$53,Inputs!$B$52+Inputs!$B$53*(1.5*I35/Inputs!$B$54-0.5*(I35/Inputs!$B$54)^3)),Inputs!$B$52+Inputs!$B$53*(1-EXP(-3*I35/Inputs!$B$54)),Inputs!$B$52+Inputs!$B$53*(1-EXP(-3*(I35/Inputs!$B$54)^2)))) -> 0.10570313
A36: 3 | B36: =A36*Inputs!$B$55 -> 300 | C36: =COUNTIFS($B$102:$U$121,">="&(B36-Inputs!$B$55/2),$B$102:$U$121,"<"&(B36+Inputs!$B$55/2))/2 -> 45 | D36: =IFERROR(AVERAGEIFS($B$102:$U$121,$B$102:$U$121,">="&(B36-Inputs!$B$55/2),$B$102:$U$121,"<"&(B36+Inputs!$B$55/2)),0) -> 302.63706 | E36: =IFERROR(AVERAGEIFS($B$125:$U$144,$B$102:$U$121,">="&(B36-Inputs!$B$55/2),$B$102:$U$121,"<"&(B36+Inputs!$B$55/2)),0) -> 0.13787306 | F36: =IF(D36=0,0,CHOOSE(Inputs!$B$51,IF(D36>=Inputs!$B$54,Inputs!$B$52+Inputs!$B$53,Inputs!$B$52+Inputs!$B$53*(1.5*D36/Inputs!$B$54-0.5*(D36/Inputs!$B$54)^3)),Inputs!$B$52+Inputs!$B$53*(1-EXP(-3*D36/Inputs!$B$54)),Inputs!$B$52+Inputs!$B$53*(1-EXP(-3*(D36/Inputs!$B$54)^2)))) -> 0.15 | G36: =C36*(E36-F36)^2 -> 0.0066178252 | I36: 100 | J36: =IF(I36=0,0,CHOOSE(Inputs!$B$51,IF(I36>=Inputs!$B$54,Inputs!$B$52+Inputs!$B$53,Inputs!$B$52+Inputs!$B$53*(1.5*I36/Inputs!$B$54-0.5*(I36/Inputs!$B$54)^3)),Inputs!$B$52+Inputs!$B$53*(1-EXP(-3*I36/Inputs!$B$54)),Inputs!$B$52+Inputs!$B$53*(1-EXP(-3*(I36/Inputs!$B$54)^2)))) -> 0.128125
A37: 4 | B37: =A37*Inputs!$B$55 -> 400 | C37: =COUNTIFS($B$102:$U$121,">="&(B37-Inputs!$B$55/2),$B$102:$U$121,"<"&(B37+Inputs!$B$55/2))/2 -> 32 | D37: =IFERROR(AVERAGEIFS($B$102:$U$121,$B$102:$U$121,">="&(B37-Inputs!$B$55/2),$B$102:$U$121,"<"&(B37+Inputs!$B$55/2)),0) -> 393.98581 | E37: =IFERROR(AVERAGEIFS($B$125:$U$144,$B$102:$U$121,">="&(B37-Inputs!$B$55/2),$B$102:$U$121,"<"&(B37+Inputs!$B$55/2)),0) -> 0.12442227 | F37: =IF(D37=0,0,CHOOSE(Inputs!$B$51,IF(D37>=Inputs!$B$54,Inputs!$B$52+Inputs!$B$53,Inputs!$B$52+Inputs!$B$53*(1.5*D37/Inputs!$B$54-0.5*(D37/Inputs!$B$54)^3)),Inputs!$B$52+Inputs!$B$53*(1-EXP(-3*D37/Inputs!$B$54)),Inputs!$B$52+Inputs!$B$53*(1-EXP(-3*(D37/Inputs!$B$54)^2)))) -> 0.15 | G37: =C37*(E37-F37)^2 -> 0.020935056 | I37: 150 | J37: =IF(I37=0,0,CHOOSE(Inputs!$B$51,IF(I37>=Inputs!$B$54,Inputs!$B$52+Inputs!$B$53,Inputs!$B$52+Inputs!$B$53*(1.5*I37/Inputs!$B$54-0.5*(I37/Inputs!$B$54)^3)),Inputs!$B$52+Inputs!$B$53*(1-EXP(-3*I37/Inputs!$B$54)),Inputs!$B$52+Inputs!$B$53*(1-EXP(-3*(I37/Inputs!$B$54)^2)))) -> 0.14398437
A38: 5 | B38: =A38*Inputs!$B$55 -> 500 | C38: =COUNTIFS($B$102:$U$121,">="&(B38-Inputs!$B$55/2),$B$102:$U$121,"<"&(B38+Inputs!$B$55/2))/2 -> 2 | D38: =IFERROR(AVERAGEIFS($B$102:$U$121,$B$102:$U$121,">="&(B38-Inputs!$B$55/2),$B$102:$U$121,"<"&(B38+Inputs!$B$55/2)),0) -> 500 | E38: =IFERROR(AVERAGEIFS($B$125:$U$144,$B$102:$U$121,">="&(B38-Inputs!$B$55/2),$B$102:$U$121,"<"&(B38+Inputs!$B$55/2)),0) -> 0.0557 | F38: =IF(D38=0,0,CHOOSE(Inputs!$B$51,IF(D38>=Inputs!$B$54,Inputs!$B$52+Inputs!$B$53,Inputs!$B$52+Inputs!$B$53*(1.5*D38/Inputs!$B$54-0.5*(D38/Inputs!$B$54)^3)),Inputs!$B$52+Inputs!$B$53*(1-EXP(-3*D38/Inputs!$B$54)),Inputs!$B$52+Inputs!$B$53*(1-EXP(-3*(D38/Inputs!$B$54)^2)))) -> 0.15 | G38: =C38*(E38-F38)^2 -> 0.01778498 | I38: 200 | J38: =IF(I38=0,0,CHOOSE(Inputs!$B$51,IF(I38>=Inputs!$B$54,Inputs!$B$52+Inputs!$B$53,Inputs!$B$52+Inputs!$B$53*(1.5*I38/Inputs!$B$54-0.5*(I38/Inputs!$B$54)^3)),Inputs!$B$52+Inputs!$B$53*(1-EXP(-3*I38/Inputs!$B$54)),Inputs!$B$52+Inputs!$B$53*(1-EXP(-3*(I38/Inputs!$B$54)^2)))) -> 0.15
A39: Total | C39: =SUM(C34:C38) -> 190 | G39: =SUM(G34:G38) -> 0.051514729 | I39: 250 | J39: =IF(I39=0,0,CHOOSE(Inputs!$B$51,IF(I39>=Inputs!$B$54,Inputs!$B$52+Inputs!$B$53,Inputs!$B$52+Inputs!$B$53*(1.5*I39/Inputs!$B$54-0.5*(I39/Inputs!$B$54)^3)),Inputs!$B$52+Inputs!$B$53*(1-EXP(-3*I39/Inputs!$B$54)),Inputs!$B$52+Inputs!$B$53*(1-EXP(-3*(I39/Inputs!$B$54)^2)))) -> 0.15
A40: Variance of the values used | B40: =VAR(G6:G25) -> 0.13835526 | C40: m² | D40: Sample variance of coal thickness (or of the residuals when the trend is removed). | I40: 300 | J40: =IF(I40=0,0,CHOOSE(Inputs!$B$51,IF(I40>=Inputs!$B$54,Inputs!$B$52+Inputs!$B$53,Inputs!$B$52+Inputs!$B$53*(1.5*I40/Inputs!$B$54-0.5*(I40/Inputs!$B$54)^3)),Inputs!$B$52+Inputs!$B$53*(1-EXP(-3*I40/Inputs!$B$54)),Inputs!$B$52+Inputs!$B$53*(1-EXP(-3*(I40/Inputs!$B$54)^2)))) -> 0.15
A41: Total sill of the model (nugget + partial sill) | B41: =Inputs!$B$52+Inputs!$B$53 -> 0.15 | C41: m² | D41: A good fit has a total sill close to the variance above. | I41: 350 | J41: =IF(I41=0,0,CHOOSE(Inputs!$B$51,IF(I41>=Inputs!$B$54,Inputs!$B$52+Inputs!$B$53,Inputs!$B$52+Inputs!$B$53*(1.5*I41/Inputs!$B$54-0.5*(I41/Inputs!$B$54)^3)),Inputs!$B$52+Inputs!$B$53*(1-EXP(-3*I41/Inputs!$B$54)),Inputs!$B$52+Inputs!$B$53*(1-EXP(-3*(I41/Inputs!$B$54)^2)))) -> 0.15
A42: Weighted RMS error of the fit | B42: =SQRT(G39/C39) -> 0.01646603 | C42: m² | D42: Smaller is better. Adjust nugget, sill and range on Inputs until the model line follows the points. | I42: 400 | J42: =IF(I42=0,0,CHOOSE(Inputs!$B$51,IF(I42>=Inputs!$B$54,Inputs!$B$52+Inputs!$B$53,Inputs!$B$52+Inputs!$B$53*(1.5*I42/Inputs!$B$54-0.5*(I42/Inputs!$B$54)^3)),Inputs!$B$52+Inputs!$B$53*(1-EXP(-3*I42/Inputs!$B$54)),Inputs!$B$52+Inputs!$B$53*(1-EXP(-3*(I42/Inputs!$B$54)^2)))) -> 0.15
A43: Twenty boreholes give a rough experimental variogram: treat the fit as indicative and refit with real data. | I43: 450 | J43: =IF(I43=0,0,CHOOSE(Inputs!$B$51,IF(I43>=Inputs!$B$54,Inputs!$B$52+Inputs!$B$53,Inputs!$B$52+Inputs!$B$53*(1.5*I43/Inputs!$B$54-0.5*(I43/Inputs!$B$54)^3)),Inputs!$B$52+Inputs!$B$53*(1-EXP(-3*I43/Inputs!$B$54)),Inputs!$B$52+Inputs!$B$53*(1-EXP(-3*(I43/Inputs!$B$54)^2)))) -> 0.15
I44: 500 | J44: =IF(I44=0,0,CHOOSE(Inputs!$B$51,IF(I44>=Inputs!$B$54,Inputs!$B$52+Inputs!$B$53,Inputs!$B$52+Inputs!$B$53*(1.5*I44/Inputs!$B$54-0.5*(I44/Inputs!$B$54)^3)),Inputs!$B$52+Inputs!$B$53*(1-EXP(-3*I44/Inputs!$B$54)),Inputs!$B$52+Inputs!$B$53*(1-EXP(-3*(I44/Inputs!$B$54)^2)))) -> 0.15
I45: 550 | J45: =IF(I45=0,0,CHOOSE(Inputs!$B$51,IF(I45>=Inputs!$B$54,Inputs!$B$52+Inputs!$B$53,Inputs!$B$52+Inputs!$B$53*(1.5*I45/Inputs!$B$54-0.5*(I45/Inputs!$B$54)^3)),Inputs!$B$52+Inputs!$B$53*(1-EXP(-3*I45/Inputs!$B$54)),Inputs!$B$52+Inputs!$B$53*(1-EXP(-3*(I45/Inputs!$B$54)^2)))) -> 0.15
I46: 600 | J46: =IF(I46=0,0,CHOOSE(Inputs!$B$51,IF(I46>=Inputs!$B$54,Inputs!$B$52+Inputs!$B$53,Inputs!$B$52+Inputs!$B$53*(1.5*I46/Inputs!$B$54-0.5*(I46/Inputs!$B$54)^3)),Inputs!$B$52+Inputs!$B$53*(1-EXP(-3*I46/Inputs!$B$54)),Inputs!$B$52+Inputs!$B$53*(1-EXP(-3*(I46/Inputs!$B$54)^2)))) -> 0.15
A62: C. Ordinary kriging at the target point
A63: Item | B63: Value | C63: Unit | D63: What it means
A64: Target X | B64: =Inputs!$B$56 -> 200 | C64: m | D64: Set on Inputs. Choose a point that is not a borehole.
A65: Target Y | B65: =Inputs!$B$57 -> 200 | C65: m | D65: Set on Inputs.
A66: Nearest borehole | B66: =INDEX($A$6:$A$25,MATCH(MIN($V$102:$V$121),$V$102:$V$121,0)) -> B2 | D66: Used by the polygon (nearest-neighbour) comparison below.
A67: Distance to nearest borehole | B67: =MIN($V$102:$V$121) -> 70.710678 | C67: m | D67: Kriging variance grows as the target moves away from data.
A68: Sum of kriging weights | B68: =SUM($Y$148:$Y$167) -> 1 | D68: Must equal 1.000 (unbiasedness condition).
A69: Lagrange multiplier, μ | B69: =$Y$168 -> 0.0043501566 | C69: m² | D69: Enforces the weights summing to 1. Enters the kriging variance.
A70: Negative weights | B70: =COUNTIF($Y$148:$Y$167,"<0") -> 0 | C70: count | D70: Negative weights can appear when closer samples screen farther ones. Large negatives need a closer look.
A71: Trend value at target, coal seam | B71: =IF(Inputs!$B$50=1,$B$29+$C$29*$B$64+$D$29*$B$65,0) -> 8.18125 | C71: m | D71: Zero when the trend switch is off.
A72: Trend value at target, overburden | B72: =IF(Inputs!$B$50=1,$B$30+$C$30*$B$64+$D$30*$B$65,0) -> 27.275 | C72: m
A73: Kriged coal seam thickness | B73: =B71+SUMPRODUCT($Y$148:$Y$167,$G$6:$G$25) -> 8.3934294 | C73: m | D73: Trend plus the kriged residual: Σ weight × value.
A74: Kriging variance | B74: =SUMPRODUCT($Y$148:$Y$167,$X$148:$X$167)+B69 -> 0.12806672 | C74: m² | D74: σ²K = Σ λᵢ γ(hᵢ0) + μ. Depends only on geometry and the variogram, not on the thickness values.
A75: Kriging standard deviation | B75: =SQRT(MAX(B74,0)) -> 0.35786411 | C75: m
A76: 95 % confidence interval, ± | B76: =1.96*B75 -> 0.70141366 | C76: m | D76: Assumes normally distributed estimation errors.
A77: Relative error | B77: =IFERROR(B76/B73,0) -> 0.083566993 | C77: % | D77: Confidence half-width as a share of the estimate.
A78: Coal thickness, nearest borehole (polygon) | B78: =INDEX($D$6:$D$25,MATCH(MIN($V$102:$V$121),$V$102:$V$121,0)) -> 8.5 | C78: m | D78: Classical polygon estimate for comparison.
A79: Coal thickness, inverse distance squared | B79: =IFERROR(SUMPRODUCT($D$6:$D$25/$V$102:$V$121^2)/SUMPRODUCT(1/$V$102:$V$121^2),B78) -> 8.3081497 | C79: m | D79: Weights = 1/h². Ignores the clustering and the trend.
A80: Kriged overburden thickness | B80: =B72+SUMPRODUCT($Y$148:$Y$167,$I$6:$I$25) -> 27.462736 | C80: m | D80: Same weights applied to overburden residuals plus its own trend.
A81: Coal in place, one block centred here | B81: =Inputs!$B$6*Inputs!$B$7*B73*Inputs!$B$8 -> 117508.01 | C81: t | D81: Block area × kriged thickness × relative density.
A82: lower limit (thickness − 95 % CI) | B82: =Inputs!$B$6*Inputs!$B$7*(B73-B76)*Inputs!$B$8 -> 107688.22 | C82: t
A83: upper limit (thickness + 95 % CI) | B83: =Inputs!$B$6*Inputs!$B$7*(B73+B76)*Inputs!$B$8 -> 127327.8 | C83: t
A84: Stripping ratio at the target | B84: =IFERROR(B80/(B73*Inputs!$B$8),0) -> 2.3370948 | C84: m³/t | D84: Overburden thickness ÷ (coal thickness × density).
A85: Kriging assumes a stationary variogram. The trend switch on Inputs removes a linear trend first (a simple form of universal kriging).
A96: D. Calculation blocks (formulas only, do not edit)
A98: Distance matrix h (m) between every pair of boreholes
A99: Block | B99: =$A$6 -> A1 | C99: =$A$7 -> A2 | D99: =$A$8 -> A3 | E99: =$A$9 -> A4 | F99: =$A$10 -> A5 | G99: =$A$11 -> B1 | H99: =$A$12 -> B2 | I99: =$A$13 -> B3 | J99: =$A$14 -> B4 | K99: =$A$15 -> B5 | L99: =$A$16 -> C1 | M99: =$A$17 -> C2 | N99: =$A$18 -> C3 | O99: =$A$19 -> C4 | P99: =$A$20 -> C5 | Q99: =$A$21 -> D1 | R99: =$A$22 -> D2 | S99: =$A$23 -> D3 | T99: =$A$24 -> D4 | U99: =$A$25 -> D5 | V99: To target (m)
A100: X (m) | B100: =$B$6 -> 50 | C100: =$B$7 -> 150 | D100: =$B$8 -> 250 | E100: =$B$9 -> 350 | F100: =$B$10 -> 450 | G100: =$B$11 -> 50 | H100: =$B$12 -> 150 | I100: =$B$13 -> 250 | J100: =$B$14 -> 350 | K100: =$B$15 -> 450 | L100: =$B$16 -> 50 | M100: =$B$17 -> 150 | N100: =$B$18 -> 250 | O100: =$B$19 -> 350 | P100: =$B$20 -> 450 | Q100: =$B$21 -> 50 | R100: =$B$22 -> 150 | S100: =$B$23 -> 250 | T100: =$B$24 -> 350 | U100: =$B$25 -> 450
A101: Y (m) | B101: =$C$6 -> 50 | C101: =$C$7 -> 50 | D101: =$C$8 -> 50 | E101: =$C$9 -> 50 | F101: =$C$10 -> 50 | G101: =$C$11 -> 150 | H101: =$C$12 -> 150 | I101: =$C$13 -> 150 | J101: =$C$14 -> 150 | K101: =$C$15 -> 150 | L101: =$C$16 -> 250 | M101: =$C$17 -> 250 | N101: =$C$18 -> 250 | O101: =$C$19 -> 250 | P101: =$C$20 -> 250 | Q101: =$C$21 -> 350 | R101: =$C$22 -> 350 | S101: =$C$23 -> 350 | T101: =$C$24 -> 350 | U101: =$C$25 -> 350
A102: =$A$6 -> A1 | B102: =SQRT(($B$6-B$100)^2+($C$6-B$101)^2) -> 0 | C102: =SQRT(($B$6-C$100)^2+($C$6-C$101)^2) -> 100 | D102: =SQRT(($B$6-D$100)^2+($C$6-D$101)^2) -> 200 | E102: =SQRT(($B$6-E$100)^2+($C$6-E$101)^2) -> 300 | F102: =SQRT(($B$6-F$100)^2+($C$6-F$101)^2) -> 400 | G102: =SQRT(($B$6-G$100)^2+($C$6-G$101)^2) -> 100 | H102: =SQRT(($B$6-H$100)^2+($C$6-H$101)^2) -> 141.42136 | I102: =SQRT(($B$6-I$100)^2+($C$6-I$101)^2) -> 223.6068 | ... U102: =SQRT(($B$6-U$100)^2+($C$6-U$101)^2) -> 500 | V102: =SQRT(($B$6-$B$64)^2+($C$6-$B$65)^2) -> 212.13203
A103: =$A$7 -> A2 | B103: =SQRT(($B$7-B$100)^2+($C$7-B$101)^2) -> 100 | C103: =SQRT(($B$7-C$100)^2+($C$7-C$101)^2) -> 0 | D103: =SQRT(($B$7-D$100)^2+($C$7-D$101)^2) -> 100 | E103: =SQRT(($B$7-E$100)^2+($C$7-E$101)^2) -> 200 | F103: =SQRT(($B$7-F$100)^2+($C$7-F$101)^2) -> 300 | G103: =SQRT(($B$7-G$100)^2+($C$7-G$101)^2) -> 141.42136 | H103: =SQRT(($B$7-H$100)^2+($C$7-H$101)^2) -> 100 | I103: =SQRT(($B$7-I$100)^2+($C$7-I$101)^2) -> 141.42136 | ... U103: =SQRT(($B$7-U$100)^2+($C$7-U$101)^2) -> 424.26407 | V103: =SQRT(($B$7-$B$64)^2+($C$7-$B$65)^2) -> 158.11388
A104: =$A$8 -> A3 | B104: =SQRT(($B$8-B$100)^2+($C$8-B$101)^2) -> 200 | C104: =SQRT(($B$8-C$100)^2+($C$8-C$101)^2) -> 100 | D104: =SQRT(($B$8-D$100)^2+($C$8-D$101)^2) -> 0 | E104: =SQRT(($B$8-E$100)^2+($C$8-E$101)^2) -> 100 | F104: =SQRT(($B$8-F$100)^2+($C$8-F$101)^2) -> 200 | G104: =SQRT(($B$8-G$100)^2+($C$8-G$101)^2) -> 223.6068 | H104: =SQRT(($B$8-H$100)^2+($C$8-H$101)^2) -> 141.42136 | I104: =SQRT(($B$8-I$100)^2+($C$8-I$101)^2) -> 100 | ... U104: =SQRT(($B$8-U$100)^2+($C$8-U$101)^2) -> 360.55513 | V104: =SQRT(($B$8-$B$64)^2+($C$8-$B$65)^2) -> 158.11388
A105: =$A$9 -> A4 | B105: =SQRT(($B$9-B$100)^2+($C$9-B$101)^2) -> 300 | C105: =SQRT(($B$9-C$100)^2+($C$9-C$101)^2) -> 200 | D105: =SQRT(($B$9-D$100)^2+($C$9-D$101)^2) -> 100 | E105: =SQRT(($B$9-E$100)^2+($C$9-E$101)^2) -> 0 | F105: =SQRT(($B$9-F$100)^2+($C$9-F$101)^2) -> 100 | G105: =SQRT(($B$9-G$100)^2+($C$9-G$101)^2) -> 316.22777 | H105: =SQRT(($B$9-H$100)^2+($C$9-H$101)^2) -> 223.6068 | I105: =SQRT(($B$9-I$100)^2+($C$9-I$101)^2) -> 141.42136 | ... U105: =SQRT(($B$9-U$100)^2+($C$9-U$101)^2) -> 316.22777 | V105: =SQRT(($B$9-$B$64)^2+($C$9-$B$65)^2) -> 212.13203
A106: =$A$10 -> A5 | B106: =SQRT(($B$10-B$100)^2+($C$10-B$101)^2) -> 400 | C106: =SQRT(($B$10-C$100)^2+($C$10-C$101)^2) -> 300 | D106: =SQRT(($B$10-D$100)^2+($C$10-D$101)^2) -> 200 | E106: =SQRT(($B$10-E$100)^2+($C$10-E$101)^2) -> 100 | F106: =SQRT(($B$10-F$100)^2+($C$10-F$101)^2) -> 0 | G106: =SQRT(($B$10-G$100)^2+($C$10-G$101)^2) -> 412.31056 | H106: =SQRT(($B$10-H$100)^2+($C$10-H$101)^2) -> 316.22777 | I106: =SQRT(($B$10-I$100)^2+($C$10-I$101)^2) -> 223.6068 | ... U106: =SQRT(($B$10-U$100)^2+($C$10-U$101)^2) -> 300 | V106: =SQRT(($B$10-$B$64)^2+($C$10-$B$65)^2) -> 291.54759
A107: =$A$11 -> B1 | B107: =SQRT(($B$11-B$100)^2+($C$11-B$101)^2) -> 100 | C107: =SQRT(($B$11-C$100)^2+($C$11-C$101)^2) -> 141.42136 | D107: =SQRT(($B$11-D$100)^2+($C$11-D$101)^2) -> 223.6068 | E107: =SQRT(($B$11-E$100)^2+($C$11-E$101)^2) -> 316.22777 | F107: =SQRT(($B$11-F$100)^2+($C$11-F$101)^2) -> 412.31056 | G107: =SQRT(($B$11-G$100)^2+($C$11-G$101)^2) -> 0 | H107: =SQRT(($B$11-H$100)^2+($C$11-H$101)^2) -> 100 | I107: =SQRT(($B$11-I$100)^2+($C$11-I$101)^2) -> 200 | ... U107: =SQRT(($B$11-U$100)^2+($C$11-U$101)^2) -> 447.2136 | V107: =SQRT(($B$11-$B$64)^2+($C$11-$B$65)^2) -> 158.11388
A108: =$A$12 -> B2 | B108: =SQRT(($B$12-B$100)^2+($C$12-B$101)^2) -> 141.42136 | C108: =SQRT(($B$12-C$100)^2+($C$12-C$101)^2) -> 100 | D108: =SQRT(($B$12-D$100)^2+($C$12-D$101)^2) -> 141.42136 | E108: =SQRT(($B$12-E$100)^2+($C$12-E$101)^2) -> 223.6068 | F108: =SQRT(($B$12-F$100)^2+($C$12-F$101)^2) -> 316.22777 | G108: =SQRT(($B$12-G$100)^2+($C$12-G$101)^2) -> 100 | H108: =SQRT(($B$12-H$100)^2+($C$12-H$101)^2) -> 0 | I108: =SQRT(($B$12-I$100)^2+($C$12-I$101)^2) -> 100 | ... U108: =SQRT(($B$12-U$100)^2+($C$12-U$101)^2) -> 360.55513 | V108: =SQRT(($B$12-$B$64)^2+($C$12-$B$65)^2) -> 70.710678
A109: =$A$13 -> B3 | B109: =SQRT(($B$13-B$100)^2+($C$13-B$101)^2) -> 223.6068 | C109: =SQRT(($B$13-C$100)^2+($C$13-C$101)^2) -> 141.42136 | D109: =SQRT(($B$13-D$100)^2+($C$13-D$101)^2) -> 100 | E109: =SQRT(($B$13-E$100)^2+($C$13-E$101)^2) -> 141.42136 | F109: =SQRT(($B$13-F$100)^2+($C$13-F$101)^2) -> 223.6068 | G109: =SQRT(($B$13-G$100)^2+($C$13-G$101)^2) -> 200 | H109: =SQRT(($B$13-H$100)^2+($C$13-H$101)^2) -> 100 | I109: =SQRT(($B$13-I$100)^2+($C$13-I$101)^2) -> 0 | ... U109: =SQRT(($B$13-U$100)^2+($C$13-U$101)^2) -> 282.84271 | V109: =SQRT(($B$13-$B$64)^2+($C$13-$B$65)^2) -> 70.710678
A110: =$A$14 -> B4 | B110: =SQRT(($B$14-B$100)^2+($C$14-B$101)^2) -> 316.22777 | C110: =SQRT(($B$14-C$100)^2+($C$14-C$101)^2) -> 223.6068 | D110: =SQRT(($B$14-D$100)^2+($C$14-D$101)^2) -> 141.42136 | E110: =SQRT(($B$14-E$100)^2+($C$14-E$101)^2) -> 100 | F110: =SQRT(($B$14-F$100)^2+($C$14-F$101)^2) -> 141.42136 | G110: =SQRT(($B$14-G$100)^2+($C$14-G$101)^2) -> 300 | H110: =SQRT(($B$14-H$100)^2+($C$14-H$101)^2) -> 200 | I110: =SQRT(($B$14-I$100)^2+($C$14-I$101)^2) -> 100 | ... U110: =SQRT(($B$14-U$100)^2+($C$14-U$101)^2) -> 223.6068 | V110: =SQRT(($B$14-$B$64)^2+($C$14-$B$65)^2) -> 158.11388
A111: =$A$15 -> B5 | B111: =SQRT(($B$15-B$100)^2+($C$15-B$101)^2) -> 412.31056 | C111: =SQRT(($B$15-C$100)^2+($C$15-C$101)^2) -> 316.22777 | D111: =SQRT(($B$15-D$100)^2+($C$15-D$101)^2) -> 223.6068 | E111: =SQRT(($B$15-E$100)^2+($C$15-E$101)^2) -> 141.42136 | F111: =SQRT(($B$15-F$100)^2+($C$15-F$101)^2) -> 100 | G111: =SQRT(($B$15-G$100)^2+($C$15-G$101)^2) -> 400 | H111: =SQRT(($B$15-H$100)^2+($C$15-H$101)^2) -> 300 | I111: =SQRT(($B$15-I$100)^2+($C$15-I$101)^2) -> 200 | ... U111: =SQRT(($B$15-U$100)^2+($C$15-U$101)^2) -> 200 | V111: =SQRT(($B$15-$B$64)^2+($C$15-$B$65)^2) -> 254.95098
A112: =$A$16 -> C1 | B112: =SQRT(($B$16-B$100)^2+($C$16-B$101)^2) -> 200 | C112: =SQRT(($B$16-C$100)^2+($C$16-C$101)^2) -> 223.6068 | D112: =SQRT(($B$16-D$100)^2+($C$16-D$101)^2) -> 282.84271 | E112: =SQRT(($B$16-E$100)^2+($C$16-E$101)^2) -> 360.55513 | F112: =SQRT(($B$16-F$100)^2+($C$16-F$101)^2) -> 447.2136 | G112: =SQRT(($B$16-G$100)^2+($C$16-G$101)^2) -> 100 | H112: =SQRT(($B$16-H$100)^2+($C$16-H$101)^2) -> 141.42136 | I112: =SQRT(($B$16-I$100)^2+($C$16-I$101)^2) -> 223.6068 | ... U112: =SQRT(($B$16-U$100)^2+($C$16-U$101)^2) -> 412.31056 | V112: =SQRT(($B$16-$B$64)^2+($C$16-$B$65)^2) -> 158.11388
A113: =$A$17 -> C2 | B113: =SQRT(($B$17-B$100)^2+($C$17-B$101)^2) -> 223.6068 | C113: =SQRT(($B$17-C$100)^2+($C$17-C$101)^2) -> 200 | D113: =SQRT(($B$17-D$100)^2+($C$17-D$101)^2) -> 223.6068 | E113: =SQRT(($B$17-E$100)^2+($C$17-E$101)^2) -> 282.84271 | F113: =SQRT(($B$17-F$100)^2+($C$17-F$101)^2) -> 360.55513 | G113: =SQRT(($B$17-G$100)^2+($C$17-G$101)^2) -> 141.42136 | H113: =SQRT(($B$17-H$100)^2+($C$17-H$101)^2) -> 100 | I113: =SQRT(($B$17-I$100)^2+($C$17-I$101)^2) -> 141.42136 | ... U113: =SQRT(($B$17-U$100)^2+($C$17-U$101)^2) -> 316.22777 | V113: =SQRT(($B$17-$B$64)^2+($C$17-$B$65)^2) -> 70.710678
A114: =$A$18 -> C3 | B114: =SQRT(($B$18-B$100)^2+($C$18-B$101)^2) -> 282.84271 | C114: =SQRT(($B$18-C$100)^2+($C$18-C$101)^2) -> 223.6068 | D114: =SQRT(($B$18-D$100)^2+($C$18-D$101)^2) -> 200 | E114: =SQRT(($B$18-E$100)^2+($C$18-E$101)^2) -> 223.6068 | F114: =SQRT(($B$18-F$100)^2+($C$18-F$101)^2) -> 282.84271 | G114: =SQRT(($B$18-G$100)^2+($C$18-G$101)^2) -> 223.6068 | H114: =SQRT(($B$18-H$100)^2+($C$18-H$101)^2) -> 141.42136 | I114: =SQRT(($B$18-I$100)^2+($C$18-I$101)^2) -> 100 | ... U114: =SQRT(($B$18-U$100)^2+($C$18-U$101)^2) -> 223.6068 | V114: =SQRT(($B$18-$B$64)^2+($C$18-$B$65)^2) -> 70.710678
A115: =$A$19 -> C4 | B115: =SQRT(($B$19-B$100)^2+($C$19-B$101)^2) -> 360.55513 | C115: =SQRT(($B$19-C$100)^2+($C$19-C$101)^2) -> 282.84271 | D115: =SQRT(($B$19-D$100)^2+($C$19-D$101)^2) -> 223.6068 | E115: =SQRT(($B$19-E$100)^2+($C$19-E$101)^2) -> 200 | F115: =SQRT(($B$19-F$100)^2+($C$19-F$101)^2) -> 223.6068 | G115: =SQRT(($B$19-G$100)^2+($C$19-G$101)^2) -> 316.22777 | H115: =SQRT(($B$19-H$100)^2+($C$19-H$101)^2) -> 223.6068 | I115: =SQRT(($B$19-I$100)^2+($C$19-I$101)^2) -> 141.42136 | ... U115: =SQRT(($B$19-U$100)^2+($C$19-U$101)^2) -> 141.42136 | V115: =SQRT(($B$19-$B$64)^2+($C$19-$B$65)^2) -> 158.11388
A116: =$A$20 -> C5 | B116: =SQRT(($B$20-B$100)^2+($C$20-B$101)^2) -> 447.2136 | C116: =SQRT(($B$20-C$100)^2+($C$20-C$101)^2) -> 360.55513 | D116: =SQRT(($B$20-D$100)^2+($C$20-D$101)^2) -> 282.84271 | E116: =SQRT(($B$20-E$100)^2+($C$20-E$101)^2) -> 223.6068 | F116: =SQRT(($B$20-F$100)^2+($C$20-F$101)^2) -> 200 | G116: =SQRT(($B$20-G$100)^2+($C$20-G$101)^2) -> 412.31056 | H116: =SQRT(($B$20-H$100)^2+($C$20-H$101)^2) -> 316.22777 | I116: =SQRT(($B$20-I$100)^2+($C$20-I$101)^2) -> 223.6068 | ... U116: =SQRT(($B$20-U$100)^2+($C$20-U$101)^2) -> 100 | V116: =SQRT(($B$20-$B$64)^2+($C$20-$B$65)^2) -> 254.95098
A117: =$A$21 -> D1 | B117: =SQRT(($B$21-B$100)^2+($C$21-B$101)^2) -> 300 | C117: =SQRT(($B$21-C$100)^2+($C$21-C$101)^2) -> 316.22777 | D117: =SQRT(($B$21-D$100)^2+($C$21-D$101)^2) -> 360.55513 | E117: =SQRT(($B$21-E$100)^2+($C$21-E$101)^2) -> 424.26407 | F117: =SQRT(($B$21-F$100)^2+($C$21-F$101)^2) -> 500 | G117: =SQRT(($B$21-G$100)^2+($C$21-G$101)^2) -> 200 | H117: =SQRT(($B$21-H$100)^2+($C$21-H$101)^2) -> 223.6068 | I117: =SQRT(($B$21-I$100)^2+($C$21-I$101)^2) -> 282.84271 | ... U117: =SQRT(($B$21-U$100)^2+($C$21-U$101)^2) -> 400 | V117: =SQRT(($B$21-$B$64)^2+($C$21-$B$65)^2) -> 212.13203
A118: =$A$22 -> D2 | B118: =SQRT(($B$22-B$100)^2+($C$22-B$101)^2) -> 316.22777 | C118: =SQRT(($B$22-C$100)^2+($C$22-C$101)^2) -> 300 | D118: =SQRT(($B$22-D$100)^2+($C$22-D$101)^2) -> 316.22777 | E118: =SQRT(($B$22-E$100)^2+($C$22-E$101)^2) -> 360.55513 | F118: =SQRT(($B$22-F$100)^2+($C$22-F$101)^2) -> 424.26407 | G118: =SQRT(($B$22-G$100)^2+($C$22-G$101)^2) -> 223.6068 | H118: =SQRT(($B$22-H$100)^2+($C$22-H$101)^2) -> 200 | I118: =SQRT(($B$22-I$100)^2+($C$22-I$101)^2) -> 223.6068 | ... U118: =SQRT(($B$22-U$100)^2+($C$22-U$101)^2) -> 300 | V118: =SQRT(($B$22-$B$64)^2+($C$22-$B$65)^2) -> 158.11388
A119: =$A$23 -> D3 | B119: =SQRT(($B$23-B$100)^2+($C$23-B$101)^2) -> 360.55513 | C119: =SQRT(($B$23-C$100)^2+($C$23-C$101)^2) -> 316.22777 | D119: =SQRT(($B$23-D$100)^2+($C$23-D$101)^2) -> 300 | E119: =SQRT(($B$23-E$100)^2+($C$23-E$101)^2) -> 316.22777 | F119: =SQRT(($B$23-F$100)^2+($C$23-F$101)^2) -> 360.55513 | G119: =SQRT(($B$23-G$100)^2+($C$23-G$101)^2) -> 282.84271 | H119: =SQRT(($B$23-H$100)^2+($C$23-H$101)^2) -> 223.6068 | I119: =SQRT(($B$23-I$100)^2+($C$23-I$101)^2) -> 200 | ... U119: =SQRT(($B$23-U$100)^2+($C$23-U$101)^2) -> 200 | V119: =SQRT(($B$23-$B$64)^2+($C$23-$B$65)^2) -> 158.11388
A120: =$A$24 -> D4 | B120: =SQRT(($B$24-B$100)^2+($C$24-B$101)^2) -> 424.26407 | C120: =SQRT(($B$24-C$100)^2+($C$24-C$101)^2) -> 360.55513 | D120: =SQRT(($B$24-D$100)^2+($C$24-D$101)^2) -> 316.22777 | E120: =SQRT(($B$24-E$100)^2+($C$24-E$101)^2) -> 300 | F120: =SQRT(($B$24-F$100)^2+($C$24-F$101)^2) -> 316.22777 | G120: =SQRT(($B$24-G$100)^2+($C$24-G$101)^2) -> 360.55513 | H120: =SQRT(($B$24-H$100)^2+($C$24-H$101)^2) -> 282.84271 | I120: =SQRT(($B$24-I$100)^2+($C$24-I$101)^2) -> 223.6068 | ... U120: =SQRT(($B$24-U$100)^2+($C$24-U$101)^2) -> 100 | V120: =SQRT(($B$24-$B$64)^2+($C$24-$B$65)^2) -> 212.13203
A121: =$A$25 -> D5 | B121: =SQRT(($B$25-B$100)^2+($C$25-B$101)^2) -> 500 | C121: =SQRT(($B$25-C$100)^2+($C$25-C$101)^2) -> 424.26407 | D121: =SQRT(($B$25-D$100)^2+($C$25-D$101)^2) -> 360.55513 | E121: =SQRT(($B$25-E$100)^2+($C$25-E$101)^2) -> 316.22777 | F121: =SQRT(($B$25-F$100)^2+($C$25-F$101)^2) -> 300 | G121: =SQRT(($B$25-G$100)^2+($C$25-G$101)^2) -> 447.2136 | H121: =SQRT(($B$25-H$100)^2+($C$25-H$101)^2) -> 360.55513 | I121: =SQRT(($B$25-I$100)^2+($C$25-I$101)^2) -> 282.84271 | ... U121: =SQRT(($B$25-U$100)^2+($C$25-U$101)^2) -> 0 | V121: =SQRT(($B$25-$B$64)^2+($C$25-$B$65)^2) -> 291.54759
A123: Observed semivariance ½ (zᵢ − zⱼ)² of the values used (m²)
A124: Block | B124: =$A$6 -> A1 | C124: =$A$7 -> A2 | D124: =$A$8 -> A3 | E124: =$A$9 -> A4 | F124: =$A$10 -> A5 | G124: =$A$11 -> B1 | H124: =$A$12 -> B2 | I124: =$A$13 -> B3 | J124: =$A$14 -> B4 | K124: =$A$15 -> B5 | L124: =$A$16 -> C1 | M124: =$A$17 -> C2 | N124: =$A$18 -> C3 | O124: =$A$19 -> C4 | P124: =$A$20 -> C5 | Q124: =$A$21 -> D1 | R124: =$A$22 -> D2 | S124: =$A$23 -> D3 | T124: =$A$24 -> D4 | U124: =$A$25 -> D5
A125: =$A$6 -> A1 | B125: =0.5*($G$6-$G$6)^2 -> 0 | C125: =0.5*($G$6-$G$7)^2 -> 0.006328125 | D125: =0.5*($G$6-$G$8)^2 -> 0.0253125 | E125: =0.5*($G$6-$G$9)^2 -> 0.056953125 | F125: =0.5*($G$6-$G$10)^2 -> 0.10125 | G125: =0.5*($G$6-$G$11)^2 -> 0.07605 | H125: =0.5*($G$6-$G$12)^2 -> 0.12625312 | I125: =0.5*($G$6-$G$13)^2 -> 0.1891125 | J125: =0.5*($G$6-$G$14)^2 -> 0.26462813 | K125: =0.5*($G$6-$G$15)^2 -> 0.0578 | L125: =0.5*($G$6-$G$16)^2 -> 0.3042 | M125: =0.5*($G$6-$G$17)^2 -> 0.39827813 | N125: =0.5*($G$6-$G$18)^2 -> 0.5050125 | O125: =0.5*($G$6-$G$19)^2 -> 0.62440312 | P125: =0.5*($G$6-$G$20)^2 -> 0.26645 | Q125: =0.5*($G$6-$G$21)^2 -> 0.01445 | R125: =0.5*($G$6-$G$22)^2 -> 0.039903125 | S125: =0.5*($G$6-$G$23)^2 -> 0.0780125 | T125: =0.5*($G$6-$G$24)^2 -> 2.8125e-05 | U125: =0.5*($G$6-$G$25)^2 -> 0.0722
A126: =$A$7 -> A2 | B126: =0.5*($G$7-$G$6)^2 -> 0.006328125 | C126: =0.5*($G$7-$G$7)^2 -> 0 | D126: =0.5*($G$7-$G$8)^2 -> 0.006328125 | E126: =0.5*($G$7-$G$9)^2 -> 0.0253125 | F126: =0.5*($G$7-$G$10)^2 -> 0.056953125 | G126: =0.5*($G$7-$G$11)^2 -> 0.038503125 | H126: =0.5*($G$7-$G$12)^2 -> 0.07605 | I126: =0.5*($G$7-$G$13)^2 -> 0.12625312 | J126: =0.5*($G$7-$G$14)^2 -> 0.1891125 | K126: =0.5*($G$7-$G$15)^2 -> 0.025878125 | L126: =0.5*($G$7-$G$16)^2 -> 0.22277812 | M126: =0.5*($G$7-$G$17)^2 -> 0.3042 | N126: =0.5*($G$7-$G$18)^2 -> 0.39827812 | O126: =0.5*($G$7-$G$19)^2 -> 0.5050125 | P126: =0.5*($G$7-$G$20)^2 -> 0.19065312 | Q126: =0.5*($G$7-$G$21)^2 -> 0.001653125 | R126: =0.5*($G$7-$G$22)^2 -> 0.01445 | S126: =0.5*($G$7-$G$23)^2 -> 0.039903125 | T126: =0.5*($G$7-$G$24)^2 -> 0.0055125 | U126: =0.5*($G$7-$G$25)^2 -> 0.12127813
A127: =$A$8 -> A3 | B127: =0.5*($G$8-$G$6)^2 -> 0.0253125 | C127: =0.5*($G$8-$G$7)^2 -> 0.006328125 | D127: =0.5*($G$8-$G$8)^2 -> 0 | E127: =0.5*($G$8-$G$9)^2 -> 0.006328125 | F127: =0.5*($G$8-$G$10)^2 -> 0.0253125 | G127: =0.5*($G$8-$G$11)^2 -> 0.0136125 | H127: =0.5*($G$8-$G$12)^2 -> 0.038503125 | I127: =0.5*($G$8-$G$13)^2 -> 0.07605 | J127: =0.5*($G$8-$G$14)^2 -> 0.12625313 | K127: =0.5*($G$8-$G$15)^2 -> 0.0066125 | L127: =0.5*($G$8-$G$16)^2 -> 0.1540125 | M127: =0.5*($G$8-$G$17)^2 -> 0.22277813 | N127: =0.5*($G$8-$G$18)^2 -> 0.3042 | O127: =0.5*($G$8-$G$19)^2 -> 0.39827813 | P127: =0.5*($G$8-$G$20)^2 -> 0.1275125 | Q127: =0.5*($G$8-$G$21)^2 -> 0.0015125 | R127: =0.5*($G$8-$G$22)^2 -> 0.001653125 | S127: =0.5*($G$8-$G$23)^2 -> 0.01445 | T127: =0.5*($G$8-$G$24)^2 -> 0.023653125 | U127: =0.5*($G$8-$G$25)^2 -> 0.1830125
A128: =$A$9 -> A4 | B128: =0.5*($G$9-$G$6)^2 -> 0.056953125 | C128: =0.5*($G$9-$G$7)^2 -> 0.0253125 | D128: =0.5*($G$9-$G$8)^2 -> 0.006328125 | E128: =0.5*($G$9-$G$9)^2 -> 0 | F128: =0.5*($G$9-$G$10)^2 -> 0.006328125 | G128: =0.5*($G$9-$G$11)^2 -> 0.001378125 | H128: =0.5*($G$9-$G$12)^2 -> 0.0136125 | I128: =0.5*($G$9-$G$13)^2 -> 0.038503125 | J128: =0.5*($G$9-$G$14)^2 -> 0.07605 | K128: =0.5*($G$9-$G$15)^2 -> 3.125e-06 | L128: =0.5*($G$9-$G$16)^2 -> 0.097903125 | M128: =0.5*($G$9-$G$17)^2 -> 0.1540125 | N128: =0.5*($G$9-$G$18)^2 -> 0.22277812 | O128: =0.5*($G$9-$G$19)^2 -> 0.3042 | P128: =0.5*($G$9-$G$20)^2 -> 0.077028125 | Q128: =0.5*($G$9-$G$21)^2 -> 0.014028125 | R128: =0.5*($G$9-$G$22)^2 -> 0.0015125 | S128: =0.5*($G$9-$G$23)^2 -> 0.001653125 | T128: =0.5*($G$9-$G$24)^2 -> 0.05445 | U128: =0.5*($G$9-$G$25)^2 -> 0.25740313
A129: =$A$10 -> A5 | B129: =0.5*($G$10-$G$6)^2 -> 0.10125 | C129: =0.5*($G$10-$G$7)^2 -> 0.056953125 | D129: =0.5*($G$10-$G$8)^2 -> 0.0253125 | E129: =0.5*($G$10-$G$9)^2 -> 0.006328125 | F129: =0.5*($G$10-$G$10)^2 -> 0 | G129: =0.5*($G$10-$G$11)^2 -> 0.0018 | H129: =0.5*($G$10-$G$12)^2 -> 0.001378125 | I129: =0.5*($G$10-$G$13)^2 -> 0.0136125 | J129: =0.5*($G$10-$G$14)^2 -> 0.038503125 | K129: =0.5*($G$10-$G$15)^2 -> 0.00605 | L129: =0.5*($G$10-$G$16)^2 -> 0.05445 | M129: =0.5*($G$10-$G$17)^2 -> 0.097903125 | N129: =0.5*($G$10-$G$18)^2 -> 0.1540125 | O129: =0.5*($G$10-$G$19)^2 -> 0.22277812 | P129: =0.5*($G$10-$G$20)^2 -> 0.0392 | Q129: =0.5*($G$10-$G$21)^2 -> 0.0392 | R129: =0.5*($G$10-$G$22)^2 -> 0.014028125 | S129: =0.5*($G$10-$G$23)^2 -> 0.0015125 | T129: =0.5*($G$10-$G$24)^2 -> 0.097903125 | U129: =0.5*($G$10-$G$25)^2 -> 0.34445
A130: =$A$11 -> B1 | B130: =0.5*($G$11-$G$6)^2 -> 0.07605 | C130: =0.5*($G$11-$G$7)^2 -> 0.038503125 | D130: =0.5*($G$11-$G$8)^2 -> 0.0136125 | E130: =0.5*($G$11-$G$9)^2 -> 0.001378125 | F130: =0.5*($G$11-$G$10)^2 -> 0.0018 | G130: =0.5*($G$11-$G$11)^2 -> 0 | H130: =0.5*($G$11-$G$12)^2 -> 0.006328125 | I130: =0.5*($G$11-$G$13)^2 -> 0.0253125 | J130: =0.5*($G$11-$G$14)^2 -> 0.056953125 | K130: =0.5*($G$11-$G$15)^2 -> 0.00125 | L130: =0.5*($G$11-$G$16)^2 -> 0.07605 | M130: =0.5*($G$11-$G$17)^2 -> 0.12625313 | N130: =0.5*($G$11-$G$18)^2 -> 0.1891125 | O130: =0.5*($G$11-$G$19)^2 -> 0.26462813 | P130: =0.5*($G$11-$G$20)^2 -> 0.0578 | Q130: =0.5*($G$11-$G$21)^2 -> 0.0242 | R130: =0.5*($G$11-$G$22)^2 -> 0.005778125 | S130: =0.5*($G$11-$G$23)^2 -> 1.25e-05 | T130: =0.5*($G$11-$G$24)^2 -> 0.073153125 | U130: =0.5*($G$11-$G$25)^2 -> 0.29645
A131: =$A$12 -> B2 | B131: =0.5*($G$12-$G$6)^2 -> 0.12625312 | C131: =0.5*($G$12-$G$7)^2 -> 0.07605 | D131: =0.5*($G$12-$G$8)^2 -> 0.038503125 | E131: =0.5*($G$12-$G$9)^2 -> 0.0136125 | F131: =0.5*($G$12-$G$10)^2 -> 0.001378125 | G131: =0.5*($G$12-$G$11)^2 -> 0.006328125 | H131: =0.5*($G$12-$G$12)^2 -> 0 | I131: =0.5*($G$12-$G$13)^2 -> 0.006328125 | J131: =0.5*($G$12-$G$14)^2 -> 0.0253125 | K131: =0.5*($G$12-$G$15)^2 -> 0.013203125 | L131: =0.5*($G$12-$G$16)^2 -> 0.038503125 | M131: =0.5*($G$12-$G$17)^2 -> 0.07605 | N131: =0.5*($G$12-$G$18)^2 -> 0.12625312 | O131: =0.5*($G$12-$G$19)^2 -> 0.1891125 | P131: =0.5*($G$12-$G$20)^2 -> 0.025878125 | Q131: =0.5*($G$12-$G$21)^2 -> 0.055278125 | R131: =0.5*($G$12-$G$22)^2 -> 0.0242 | S131: =0.5*($G$12-$G$23)^2 -> 0.005778125 | T131: =0.5*($G$12-$G$24)^2 -> 0.1225125 | U131: =0.5*($G$12-$G$25)^2 -> 0.38940312
A132: =$A$13 -> B3 | B132: =0.5*($G$13-$G$6)^2 -> 0.1891125 | C132: =0.5*($G$13-$G$7)^2 -> 0.12625312 | D132: =0.5*($G$13-$G$8)^2 -> 0.07605 | E132: =0.5*($G$13-$G$9)^2 -> 0.038503125 | F132: =0.5*($G$13-$G$10)^2 -> 0.0136125 | G132: =0.5*($G$13-$G$11)^2 -> 0.0253125 | H132: =0.5*($G$13-$G$12)^2 -> 0.006328125 | I132: =0.5*($G$13-$G$13)^2 -> 0 | J132: =0.5*($G$13-$G$14)^2 -> 0.006328125 | K132: =0.5*($G$13-$G$15)^2 -> 0.0378125 | L132: =0.5*($G$13-$G$16)^2 -> 0.0136125 | M132: =0.5*($G$13-$G$17)^2 -> 0.038503125 | N132: =0.5*($G$13-$G$18)^2 -> 0.07605 | O132: =0.5*($G$13-$G$19)^2 -> 0.12625313 | P132: =0.5*($G$13-$G$20)^2 -> 0.0066125 | Q132: =0.5*($G$13-$G$21)^2 -> 0.0990125 | R132: =0.5*($G$13-$G$22)^2 -> 0.055278125 | S132: =0.5*($G$13-$G$23)^2 -> 0.0242 | T132: =0.5*($G$13-$G$24)^2 -> 0.18452812 | U132: =0.5*($G$13-$G$25)^2 -> 0.4950125
A133: =$A$14 -> B4 | B133: =0.5*($G$14-$G$6)^2 -> 0.26462813 | C133: =0.5*($G$14-$G$7)^2 -> 0.1891125 | D133: =0.5*($G$14-$G$8)^2 -> 0.12625313 | E133: =0.5*($G$14-$G$9)^2 -> 0.07605 | F133: =0.5*($G$14-$G$10)^2 -> 0.038503125 | G133: =0.5*($G$14-$G$11)^2 -> 0.056953125 | H133: =0.5*($G$14-$G$12)^2 -> 0.0253125 | I133: =0.5*($G$14-$G$13)^2 -> 0.006328125 | J133: =0.5*($G$14-$G$14)^2 -> 0 | K133: =0.5*($G$14-$G$15)^2 -> 0.075078125 | L133: =0.5*($G$14-$G$16)^2 -> 0.001378125 | M133: =0.5*($G$14-$G$17)^2 -> 0.0136125 | N133: =0.5*($G$14-$G$18)^2 -> 0.038503125 | O133: =0.5*($G$14-$G$19)^2 -> 0.07605 | P133: =0.5*($G$14-$G$20)^2 -> 3.125e-06 | Q133: =0.5*($G$14-$G$21)^2 -> 0.15540313 | R133: =0.5*($G$14-$G$22)^2 -> 0.0990125 | S133: =0.5*($G$14-$G$23)^2 -> 0.055278125 | T133: =0.5*($G$14-$G$24)^2 -> 0.2592 | U133: =0.5*($G$14-$G$25)^2 -> 0.61327812
A134: =$A$15 -> B5 | B134: =0.5*($G$15-$G$6)^2 -> 0.0578 | C134: =0.5*($G$15-$G$7)^2 -> 0.025878125 | D134: =0.5*($G$15-$G$8)^2 -> 0.0066125 | E134: =0.5*($G$15-$G$9)^2 -> 3.125e-06 | F134: =0.5*($G$15-$G$10)^2 -> 0.00605 | G134: =0.5*($G$15-$G$11)^2 -> 0.00125 | H134: =0.5*($G$15-$G$12)^2 -> 0.013203125 | I134: =0.5*($G$15-$G$13)^2 -> 0.0378125 | J134: =0.5*($G$15-$G$14)^2 -> 0.075078125 | K134: =0.5*($G$15-$G$15)^2 -> 0 | L134: =0.5*($G$15-$G$16)^2 -> 0.0968 | M134: =0.5*($G$15-$G$17)^2 -> 0.15262813 | N134: =0.5*($G$15-$G$18)^2 -> 0.2211125 | O134: =0.5*($G$15-$G$19)^2 -> 0.30225312 | P134: =0.5*($G$15-$G$20)^2 -> 0.07605 | Q134: =0.5*($G$15-$G$21)^2 -> 0.01445 | R134: =0.5*($G$15-$G$22)^2 -> 0.001653125 | S134: =0.5*($G$15-$G$23)^2 -> 0.0015125 | T134: =0.5*($G$15-$G$24)^2 -> 0.055278125 | U134: =0.5*($G$15-$G$25)^2 -> 0.2592
A135: =$A$16 -> C1 | B135: =0.5*($G$16-$G$6)^2 -> 0.3042 | C135: =0.5*($G$16-$G$7)^2 -> 0.22277812 | D135: =0.5*($G$16-$G$8)^2 -> 0.1540125 | E135: =0.5*($G$16-$G$9)^2 -> 0.097903125 | F135: =0.5*($G$16-$G$10)^2 -> 0.05445 | G135: =0.5*($G$16-$G$11)^2 -> 0.07605 | H135: =0.5*($G$16-$G$12)^2 -> 0.038503125 | I135: =0.5*($G$16-$G$13)^2 -> 0.0136125 | J135: =0.5*($G$16-$G$14)^2 -> 0.001378125 | K135: =0.5*($G$16-$G$15)^2 -> 0.0968 | L135: =0.5*($G$16-$G$16)^2 -> 0 | M135: =0.5*($G$16-$G$17)^2 -> 0.006328125 | N135: =0.5*($G$16-$G$18)^2 -> 0.0253125 | O135: =0.5*($G$16-$G$19)^2 -> 0.056953125 | P135: =0.5*($G$16-$G$20)^2 -> 0.00125 | Q135: =0.5*($G$16-$G$21)^2 -> 0.18605 | R135: =0.5*($G$16-$G$22)^2 -> 0.12375312 | S135: =0.5*($G$16-$G$23)^2 -> 0.0741125 | T135: =0.5*($G$16-$G$24)^2 -> 0.29837812 | U135: =0.5*($G$16-$G$25)^2 -> 0.6728
A136: =$A$17 -> C2 | B136: =0.5*($G$17-$G$6)^2 -> 0.39827813 | C136: =0.5*($G$17-$G$7)^2 -> 0.3042 | D136: =0.5*($G$17-$G$8)^2 -> 0.22277813 | E136: =0.5*($G$17-$G$9)^2 -> 0.1540125 | F136: =0.5*($G$17-$G$10)^2 -> 0.097903125 | G136: =0.5*($G$17-$G$11)^2 -> 0.12625313 | H136: =0.5*($G$17-$G$12)^2 -> 0.07605 | I136: =0.5*($G$17-$G$13)^2 -> 0.038503125 | J136: =0.5*($G$17-$G$14)^2 -> 0.0136125 | K136: =0.5*($G$17-$G$15)^2 -> 0.15262813 | L136: =0.5*($G$17-$G$16)^2 -> 0.006328125 | M136: =0.5*($G$17-$G$17)^2 -> 0 | N136: =0.5*($G$17-$G$18)^2 -> 0.006328125 | O136: =0.5*($G$17-$G$19)^2 -> 0.0253125 | P136: =0.5*($G$17-$G$20)^2 -> 0.013203125 | Q136: =0.5*($G$17-$G$21)^2 -> 0.26100313 | R136: =0.5*($G$17-$G$22)^2 -> 0.18605 | S136: =0.5*($G$17-$G$23)^2 -> 0.12375313 | T136: =0.5*($G$17-$G$24)^2 -> 0.3916125 | U136: =0.5*($G$17-$G$25)^2 -> 0.80962812
A137: =$A$18 -> C3 | B137: =0.5*($G$18-$G$6)^2 -> 0.5050125 | C137: =0.5*($G$18-$G$7)^2 -> 0.39827812 | D137: =0.5*($G$18-$G$8)^2 -> 0.3042 | E137: =0.5*($G$18-$G$9)^2 -> 0.22277812 | F137: =0.5*($G$18-$G$10)^2 -> 0.1540125 | G137: =0.5*($G$18-$G$11)^2 -> 0.1891125 | H137: =0.5*($G$18-$G$12)^2 -> 0.12625312 | I137: =0.5*($G$18-$G$13)^2 -> 0.07605 | J137: =0.5*($G$18-$G$14)^2 -> 0.038503125 | K137: =0.5*($G$18-$G$15)^2 -> 0.2211125 | L137: =0.5*($G$18-$G$16)^2 -> 0.0253125 | M137: =0.5*($G$18-$G$17)^2 -> 0.006328125 | N137: =0.5*($G$18-$G$18)^2 -> 0 | O137: =0.5*($G$18-$G$19)^2 -> 0.006328125 | P137: =0.5*($G$18-$G$20)^2 -> 0.0378125 | Q137: =0.5*($G$18-$G$21)^2 -> 0.3486125 | R137: =0.5*($G$18-$G$22)^2 -> 0.26100312 | S137: =0.5*($G$18-$G$23)^2 -> 0.18605 | T137: =0.5*($G$18-$G$24)^2 -> 0.49750312 | U137: =0.5*($G$18-$G$25)^2 -> 0.9591125
...

Sheet Pit design
A1: Pit design — benches, overall slope, slope-wedge overburden and slope stability
A2: Bench geometry gives the overall pit slope. Each pit wall adds a wedge of overburden that no borehole shows. A planar-failure check tests whether the slope will stand.
A4: A. Pit walls and slope-wedge overburden, block by block
A5: Block | B5: Pit depth (m) | C5: Economic (1 = yes) | D5: Benches | E5: Overall slope (degrees) | F5: North wall | G5: South wall | H5: West wall | I5: East wall | J5: Wall length (m) | K5: Wall depth (m) | L5: Wedge volume (BCM)
A6: =Reserve!A6 -> A1 | B6: =Reserve!B6+Reserve!C6 -> 26.5 | C6: =IF(Reserve!I6="Yes",1,0) -> 1 | D6: =ROUNDUP(B6/Inputs!$B$59,0) -> 3 | E6: =DEGREES(ATAN(B6/(B6/TAN(RADIANS(Inputs!$B$60))+(D6-1)*Inputs!$B$61))) -> 45.939135 | F6: =IF($C6=1,IF(IFERROR(INDEX($C$6:$C$25,MATCH(CHAR(CODE(LEFT($A6,1))-1)&MID($A6,2,9),$A$6:$A$25,0)),0)=1,0,1),0) -> 1 | G6: =IF($C6=1,IF(IFERROR(INDEX($C$6:$C$25,MATCH(CHAR(CODE(LEFT($A6,1))+1)&MID($A6,2,9),$A$6:$A$25,0)),0)=1,0,1),0) -> 0 | H6: =IF($C6=1,IF(IFERROR(INDEX($C$6:$C$25,MATCH(LEFT($A6,1)&(VALUE(MID($A6,2,9))-1),$A$6:$A$25,0)),0)=1,0,1),0) -> 1 | I6: =IF($C6=1,IF(IFERROR(INDEX($C$6:$C$25,MATCH(LEFT($A6,1)&(VALUE(MID($A6,2,9))+1),$A$6:$A$25,0)),0)=1,0,1),0) -> 0 | J6: =(F6+G6)*Inputs!$B$6+(H6+I6)*Inputs!$B$7 -> 200 | K6: =IF(J6>0,B6,0) -> 26.5 | L6: =J6*0.5*B6^2/TAN(RADIANS(E6)) -> 67959.81
A7: =Reserve!A7 -> A2 | B7: =Reserve!B7+Reserve!C7 -> 31 | C7: =IF(Reserve!I7="Yes",1,0) -> 1 | D7: =ROUNDUP(B7/Inputs!$B$59,0) -> 4 | E7: =DEGREES(ATAN(B7/(B7/TAN(RADIANS(Inputs!$B$60))+(D7-1)*Inputs!$B$61))) -> 41.302804 | F7: =IF($C7=1,IF(IFERROR(INDEX($C$6:$C$25,MATCH(CHAR(CODE(LEFT($A7,1))-1)&MID($A7,2,9),$A$6:$A$25,0)),0)=1,0,1),0) -> 1 | G7: =IF($C7=1,IF(IFERROR(INDEX($C$6:$C$25,MATCH(CHAR(CODE(LEFT($A7,1))+1)&MID($A7,2,9),$A$6:$A$25,0)),0)=1,0,1),0) -> 0 | H7: =IF($C7=1,IF(IFERROR(INDEX($C$6:$C$25,MATCH(LEFT($A7,1)&(VALUE(MID($A7,2,9))-1),$A$6:$A$25,0)),0)=1,0,1),0) -> 0 | I7: =IF($C7=1,IF(IFERROR(INDEX($C$6:$C$25,MATCH(LEFT($A7,1)&(VALUE(MID($A7,2,9))+1),$A$6:$A$25,0)),0)=1,0,1),0) -> 0 | J7: =(F7+G7)*Inputs!$B$6+(H7+I7)*Inputs!$B$7 -> 100 | K7: =IF(J7>0,B7,0) -> 31 | L7: =J7*0.5*B7^2/TAN(RADIANS(E7)) -> 54688.77
A8: =Reserve!A8 -> A3 | B8: =Reserve!B8+Reserve!C8 -> 36.5 | C8: =IF(Reserve!I8="Yes",1,0) -> 1 | D8: =ROUNDUP(B8/Inputs!$B$59,0) -> 4 | E8: =DEGREES(ATAN(B8/(B8/TAN(RADIANS(Inputs!$B$60))+(D8-1)*Inputs!$B$61))) -> 44.390519 | F8: =IF($C8=1,IF(IFERROR(INDEX($C$6:$C$25,MATCH(CHAR(CODE(LEFT($A8,1))-1)&MID($A8,2,9),$A$6:$A$25,0)),0)=1,0,1),0) -> 1 | G8: =IF($C8=1,IF(IFERROR(INDEX($C$6:$C$25,MATCH(CHAR(CODE(LEFT($A8,1))+1)&MID($A8,2,9),$A$6:$A$25,0)),0)=1,0,1),0) -> 0 | H8: =IF($C8=1,IF(IFERROR(INDEX($C$6:$C$25,MATCH(LEFT($A8,1)&(VALUE(MID($A8,2,9))-1),$A$6:$A$25,0)),0)=1,0,1),0) -> 0 | I8: =IF($C8=1,IF(IFERROR(INDEX($C$6:$C$25,MATCH(LEFT($A8,1)&(VALUE(MID($A8,2,9))+1),$A$6:$A$25,0)),0)=1,0,1),0) -> 0 | J8: =(F8+G8)*Inputs!$B$6+(H8+I8)*Inputs!$B$7 -> 100 | K8: =IF(J8>0,B8,0) -> 36.5 | L8: =J8*0.5*B8^2/TAN(RADIANS(E8)) -> 68044.967
A9: =Reserve!A9 -> A4 | B9: =Reserve!B9+Reserve!C9 -> 43 | C9: =IF(Reserve!I9="Yes",1,0) -> 1 | D9: =ROUNDUP(B9/Inputs!$B$59,0) -> 5 | E9: =DEGREES(ATAN(B9/(B9/TAN(RADIANS(Inputs!$B$60))+(D9-1)*Inputs!$B$61))) -> 42.063088 | F9: =IF($C9=1,IF(IFERROR(INDEX($C$6:$C$25,MATCH(CHAR(CODE(LEFT($A9,1))-1)&MID($A9,2,9),$A$6:$A$25,0)),0)=1,0,1),0) -> 1 | G9: =IF($C9=1,IF(IFERROR(INDEX($C$6:$C$25,MATCH(CHAR(CODE(LEFT($A9,1))+1)&MID($A9,2,9),$A$6:$A$25,0)),0)=1,0,1),0) -> 0 | H9: =IF($C9=1,IF(IFERROR(INDEX($C$6:$C$25,MATCH(LEFT($A9,1)&(VALUE(MID($A9,2,9))-1),$A$6:$A$25,0)),0)=1,0,1),0) -> 0 | I9: =IF($C9=1,IF(IFERROR(INDEX($C$6:$C$25,MATCH(LEFT($A9,1)&(VALUE(MID($A9,2,9))+1),$A$6:$A$25,0)),0)=1,0,1),0) -> 1 | J9: =(F9+G9)*Inputs!$B$6+(H9+I9)*Inputs!$B$7 -> 200 | K9: =IF(J9>0,B9,0) -> 43 | L9: =J9*0.5*B9^2/TAN(RADIANS(E9)) -> 204898.1
A10: =Reserve!A10 -> A5 | B10: =Reserve!B10+Reserve!C10 -> 51.5 | C10: =IF(Reserve!I10="Yes",1,0) -> 0 | D10: =ROUNDUP(B10/Inputs!$B$59,0) -> 6 | E10: =DEGREES(ATAN(B10/(B10/TAN(RADIANS(Inputs!$B$60))+(D10-1)*Inputs!$B$61))) -> 41.240342 | F10: =IF($C10=1,IF(IFERROR(INDEX($C$6:$C$25,MATCH(CHAR(CODE(LEFT($A10,1))-1)&MID($A10,2,9),$A$6:$A$25,0)),0)=1,0,1),0) -> 0 | G10: =IF($C10=1,IF(IFERROR(INDEX($C$6:$C$25,MATCH(CHAR(CODE(LEFT($A10,1))+1)&MID($A10,2,9),$A$6:$A$25,0)),0)=1,0,1),0) -> 0 | H10: =IF($C10=1,IF(IFERROR(INDEX($C$6:$C$25,MATCH(LEFT($A10,1)&(VALUE(MID($A10,2,9))-1),$A$6:$A$25,0)),0)=1,0,1),0) -> 0 | I10: =IF($C10=1,IF(IFERROR(INDEX($C$6:$C$25,MATCH(LEFT($A10,1)&(VALUE(MID($A10,2,9))+1),$A$6:$A$25,0)),0)=1,0,1),0) -> 0 | J10: =(F10+G10)*Inputs!$B$6+(H10+I10)*Inputs!$B$7 -> 0 | K10: =IF(J10>0,B10,0) -> 0 | L10: =J10*0.5*B10^2/TAN(RADIANS(E10)) -> 0
A11: =Reserve!A11 -> B1 | B11: =Reserve!B11+Reserve!C11 -> 29 | C11: =IF(Reserve!I11="Yes",1,0) -> 1 | D11: =ROUNDUP(B11/Inputs!$B$59,0) -> 3 | E11: =DEGREES(ATAN(B11/(B11/TAN(RADIANS(Inputs!$B$60))+(D11-1)*Inputs!$B$61))) -> 47.519839 | F11: =IF($C11=1,IF(IFERROR(INDEX($C$6:$C$25,MATCH(CHAR(CODE(LEFT($A11,1))-1)&MID($A11,2,9),$A$6:$A$25,0)),0)=1,0,1),0) -> 0 | G11: =IF($C11=1,IF(IFERROR(INDEX($C$6:$C$25,MATCH(CHAR(CODE(LEFT($A11,1))+1)&MID($A11,2,9),$A$6:$A$25,0)),0)=1,0,1),0) -> 0 | H11: =IF($C11=1,IF(IFERROR(INDEX($C$6:$C$25,MATCH(LEFT($A11,1)&(VALUE(MID($A11,2,9))-1),$A$6:$A$25,0)),0)=1,0,1),0) -> 1 | I11: =IF($C11=1,IF(IFERROR(INDEX($C$6:$C$25,MATCH(LEFT($A11,1)&(VALUE(MID($A11,2,9))+1),$A$6:$A$25,0)),0)=1,0,1),0) -> 0 | J11: =(F11+G11)*Inputs!$B$6+(H11+I11)*Inputs!$B$7 -> 100 | K11: =IF(J11>0,B11,0) -> 29 | L11: =J11*0.5*B11^2/TAN(RADIANS(E11)) -> 38504.948
A12: =Reserve!A12 -> B2 | B12: =Reserve!B12+Reserve!C12 -> 33.5 | C12: =IF(Reserve!I12="Yes",1,0) -> 1 | D12: =ROUNDUP(B12/Inputs!$B$59,0) -> 4 | E12: =DEGREES(ATAN(B12/(B12/TAN(RADIANS(Inputs!$B$60))+(D12-1)*Inputs!$B$61))) -> 42.787138 | F12: =IF($C12=1,IF(IFERROR(INDEX($C$6:$C$25,MATCH(CHAR(CODE(LEFT($A12,1))-1)&MID($A12,2,9),$A$6:$A$25,0)),0)=1,0,1),0) -> 0 | G12: =IF($C12=1,IF(IFERROR(INDEX($C$6:$C$25,MATCH(CHAR(CODE(LEFT($A12,1))+1)&MID($A12,2,9),$A$6:$A$25,0)),0)=1,0,1),0) -> 0 | H12: =IF($C12=1,IF(IFERROR(INDEX($C$6:$C$25,MATCH(LEFT($A12,1)&(VALUE(MID($A12,2,9))-1),$A$6:$A$25,0)),0)=1,0,1),0) -> 0 | I12: =IF($C12=1,IF(IFERROR(INDEX($C$6:$C$25,MATCH(LEFT($A12,1)&(VALUE(MID($A12,2,9))+1),$A$6:$A$25,0)),0)=1,0,1),0) -> 0 | J12: =(F12+G12)*Inputs!$B$6+(H12+I12)*Inputs!$B$7 -> 0 | K12: =IF(J12>0,B12,0) -> 0 | L12: =J12*0.5*B12^2/TAN(RADIANS(E12)) -> 0
A13: =Reserve!A13 -> B3 | B13: =Reserve!B13+Reserve!C13 -> 39 | C13: =IF(Reserve!I13="Yes",1,0) -> 1 | D13: =ROUNDUP(B13/Inputs!$B$59,0) -> 4 | E13: =DEGREES(ATAN(B13/(B13/TAN(RADIANS(Inputs!$B$60))+(D13-1)*Inputs!$B$61))) -> 45.597587 | F13: =IF($C13=1,IF(IFERROR(INDEX($C$6:$C$25,MATCH(CHAR(CODE(LEFT($A13,1))-1)&MID($A13,2,9),$A$6:$A$25,0)),0)=1,0,1),0) -> 0 | G13: =IF($C13=1,IF(IFERROR(INDEX($C$6:$C$25,MATCH(CHAR(CODE(LEFT($A13,1))+1)&MID($A13,2,9),$A$6:$A$25,0)),0)=1,0,1),0) -> 0 | H13: =IF($C13=1,IF(IFERROR(INDEX($C$6:$C$25,MATCH(LEFT($A13,1)&(VALUE(MID($A13,2,9))-1),$A$6:$A$25,0)),0)=1,0,1),0) -> 0 | I13: =IF($C13=1,IF(IFERROR(INDEX($C$6:$C$25,MATCH(LEFT($A13,1)&(VALUE(MID($A13,2,9))+1),$A$6:$A$25,0)),0)=1,0,1),0) -> 0 | J13: =(F13+G13)*Inputs!$B$6+(H13+I13)*Inputs!$B$7 -> 0 | K13: =IF(J13>0,B13,0) -> 0 | L13: =J13*0.5*B13^2/TAN(RADIANS(E13)) -> 0
A14: =Reserve!A14 -> B4 | B14: =Reserve!B14+Reserve!C14 -> 45.5 | C14: =IF(Reserve!I14="Yes",1,0) -> 1 | D14: =ROUNDUP(B14/Inputs!$B$59,0) -> 5 | E14: =DEGREES(ATAN(B14/(B14/TAN(RADIANS(Inputs!$B$60))+(D14-1)*Inputs!$B$61))) -> 43.136306 | F14: =IF($C14=1,IF(IFERROR(INDEX($C$6:$C$25,MATCH(CHAR(CODE(LEFT($A14,1))-1)&MID($A14,2,9),$A$6:$A$25,0)),0)=1,0,1),0) -> 0 | G14: =IF($C14=1,IF(IFERROR(INDEX($C$6:$C$25,MATCH(CHAR(CODE(LEFT($A14,1))+1)&MID($A14,2,9),$A$6:$A$25,0)),0)=1,0,1),0) -> 0 | H14: =IF($C14=1,IF(IFERROR(INDEX($C$6:$C$25,MATCH(LEFT($A14,1)&(VALUE(MID($A14,2,9))-1),$A$6:$A$25,0)),0)=1,0,1),0) -> 0 | I14: =IF($C14=1,IF(IFERROR(INDEX($C$6:$C$25,MATCH(LEFT($A14,1)&(VALUE(MID($A14,2,9))+1),$A$6:$A$25,0)),0)=1,0,1),0) -> 1 | J14: =(F14+G14)*Inputs!$B$6+(H14+I14)*Inputs!$B$7 -> 100 | K14: =IF(J14>0,B14,0) -> 45.5 | L14: =J14*0.5*B14^2/TAN(RADIANS(E14)) -> 110475.47
A15: =Reserve!A15 -> B5 | B15: =Reserve!B15+Reserve!C15 -> 53.5 | C15: =IF(Reserve!I15="Yes",1,0) -> 0 | D15: =ROUNDUP(B15/Inputs!$B$59,0) -> 6 | E15: =DEGREES(ATAN(B15/(B15/TAN(RADIANS(Inputs!$B$60))+(D15-1)*Inputs!$B$61))) -> 41.973814 | F15: =IF($C15=1,IF(IFERROR(INDEX($C$6:$C$25,MATCH(CHAR(CODE(LEFT($A15,1))-1)&MID($A15,2,9),$A$6:$A$25,0)),0)=1,0,1),0) -> 0 | G15: =IF($C15=1,IF(IFERROR(INDEX($C$6:$C$25,MATCH(CHAR(CODE(LEFT($A15,1))+1)&MID($A15,2,9),$A$6:$A$25,0)),0)=1,0,1),0) -> 0 | H15: =IF($C15=1,IF(IFERROR(INDEX($C$6:$C$25,MATCH(LEFT($A15,1)&(VALUE(MID($A15,2,9))-1),$A$6:$A$25,0)),0)=1,0,1),0) -> 0 | I15: =IF($C15=1,IF(IFERROR(INDEX($C$6:$C$25,MATCH(LEFT($A15,1)&(VALUE(MID($A15,2,9))+1),$A$6:$A$25,0)),0)=1,0,1),0) -> 0 | J15: =(F15+G15)*Inputs!$B$6+(H15+I15)*Inputs!$B$7 -> 0 | K15: =IF(J15>0,B15,0) -> 0 | L15: =J15*0.5*B15^2/TAN(RADIANS(E15)) -> 0
A16: =Reserve!A16 -> C1 | B16: =Reserve!B16+Reserve!C16 -> 28.5 | C16: =IF(Reserve!I16="Yes",1,0) -> 1 | D16: =ROUNDUP(B16/Inputs!$B$59,0) -> 3 | E16: =DEGREES(ATAN(B16/(B16/TAN(RADIANS(Inputs!$B$60))+(D16-1)*Inputs!$B$61))) -> 47.219637 | F16: =IF($C16=1,IF(IFERROR(INDEX($C$6:$C$25,MATCH(CHAR(CODE(LEFT($A16,1))-1)&MID($A16,2,9),$A$6:$A$25,0)),0)=1,0,1),0) -> 0 | G16: =IF($C16=1,IF(IFERROR(INDEX($C$6:$C$25,MATCH(CHAR(CODE(LEFT($A16,1))+1)&MID($A16,2,9),$A$6:$A$25,0)),0)=1,0,1),0) -> 0 | H16: =IF($C16=1,IF(IFERROR(INDEX($C$6:$C$25,MATCH(LEFT($A16,1)&(VALUE(MID($A16,2,9))-1),$A$6:$A$25,0)),0)=1,0,1),0) -> 1 | I16: =IF($C16=1,IF(IFERROR(INDEX($C$6:$C$25,MATCH(LEFT($A16,1)&(VALUE(MID($A16,2,9))+1),$A$6:$A$25,0)),0)=1,0,1),0) -> 0 | J16: =(F16+G16)*Inputs!$B$6+(H16+I16)*Inputs!$B$7 -> 100 | K16: =IF(J16>0,B16,0) -> 28.5 | L16: =J16*0.5*B16^2/TAN(RADIANS(E16)) -> 37581.741
A17: =Reserve!A17 -> C2 | B17: =Reserve!B17+Reserve!C17 -> 33 | C17: =IF(Reserve!I17="Yes",1,0) -> 1 | D17: =ROUNDUP(B17/Inputs!$B$59,0) -> 4 | E17: =DEGREES(ATAN(B17/(B17/TAN(RADIANS(Inputs!$B$60))+(D17-1)*Inputs!$B$61))) -> 42.501714 | F17: =IF($C17=1,IF(IFERROR(INDEX($C$6:$C$25,MATCH(CHAR(CODE(LEFT($A17,1))-1)&MID($A17,2,9),$A$6:$A$25,0)),0)=1,0,1),0) -> 0 | G17: =IF($C17=1,IF(IFERROR(INDEX($C$6:$C$25,MATCH(CHAR(CODE(LEFT($A17,1))+1)&MID($A17,2,9),$A$6:$A$25,0)),0)=1,0,1),0) -> 0 | H17: =IF($C17=1,IF(IFERROR(INDEX($C$6:$C$25,MATCH(LEFT($A17,1)&(VALUE(MID($A17,2,9))-1),$A$6:$A$25,0)),0)=1,0,1),0) -> 0 | I17: =IF($C17=1,IF(IFERROR(INDEX($C$6:$C$25,MATCH(LEFT($A17,1)&(VALUE(MID($A17,2,9))+1),$A$6:$A$25,0)),0)=1,0,1),0) -> 0 | J17: =(F17+G17)*Inputs!$B$6+(H17+I17)*Inputs!$B$7 -> 0 | K17: =IF(J17>0,B17,0) -> 0 | L17: =J17*0.5*B17^2/TAN(RADIANS(E17)) -> 0
... A25: =Reserve!A25 -> D5 | B25: =Reserve!B25+Reserve!C25 -> 49 | C25: =IF(Reserve!I25="Yes",1,0) -> 0 | D25: =ROUNDUP(B25/Inputs!$B$59,0) -> 5 | E25: =DEGREES(ATAN(B25/(B25/TAN(RADIANS(Inputs!$B$60))+(D25-1)*Inputs!$B$61))) -> 44.516216 | F25: =IF($C25=1,IF(IFERROR(INDEX($C$6:$C$25,MATCH(CHAR(CODE(LEFT($A25,1))-1)&MID($A25,2,9),$A$6:$A$25,0)),0)=1,0,1),0) -> 0 | G25: =IF($C25=1,IF(IFERROR(INDEX($C$6:$C$25,MATCH(CHAR(CODE(LEFT($A25,1))+1)&MID($A25,2,9),$A$6:$A$25,0)),0)=1,0,1),0) -> 0 | H25: =IF($C25=1,IF(IFERROR(INDEX($C$6:$C$25,MATCH(LEFT($A25,1)&(VALUE(MID($A25,2,9))-1),$A$6:$A$25,0)),0)=1,0,1),0) -> 0 | I25: =IF($C25=1,IF(IFERROR(INDEX($C$6:$C$25,MATCH(LEFT($A25,1)&(VALUE(MID($A25,2,9))+1),$A$6:$A$25,0)),0)=1,0,1),0) -> 0 | J25: =(F25+G25)*Inputs!$B$6+(H25+I25)*Inputs!$B$7 -> 0 | K25: =IF(J25>0,B25,0) -> 0 | L25: =J25*0.5*B25^2/TAN(RADIANS(E25)) -> 0
A26: Total / deepest wall | C26: =SUM(C6:C25) -> 16 | J26: =SUM(J6:J25) -> 1600 | K26: =MAX(K6:K25) -> 45.5 | L26: =SUM(L6:L25) -> 1076129
A27: A wall exists where an economic block meets the grid edge or a block left unmined (flag 1). Corner wedges are ignored. Overall slope: tan β = D ÷ (D ÷ tan α + (N − 1) × berm).
A29: B. Effect on the stripping ratio
A30: Item | B30: Value | C30: Unit | D30: What it means
A31: Overburden in economic blocks | B31: =Reserve!B37 -> 4320000 | C31: BCM | D31: Block-by-block overburden from the Reserve sheet.
A32: Slope-wedge overburden | B32: =L26 -> 1076129 | C32: BCM | D32: Extra rock to cut back the pit walls: ½ × D² × cot β per metre of wall.
A33: Wedge switch (Inputs) | B33: =Inputs!$B$46 -> 1 | C33: 1 or 0 | D33: 1 includes the wedge in the stripping ratio used by Fleet, Economics and Cash flow.
A34: Overburden to remove, including wedge | B34: =B31+B33*B32 -> 5396129 | C34: BCM
A35: Coal in place, economic blocks | B35: =Reserve!B36 -> 1841000 | C35: t
A36: Stripping ratio, blocks only | B36: =IFERROR(B31/B35,0) -> 2.3465508 | C36: m³/t | D36: What the simple block model gives.
A37: Stripping ratio including pit slopes | B37: =IFERROR(B34/B35,0) -> 2.9310858 | C37: m³/t | D37: Feeds the Reserve sheet (stripping ratio, economic blocks).
A38: Increase due to pit slopes | B38: =IFERROR(B37/B36-1,0) -> 0.24910393 | C38: %
A40: C. Planar-failure factor of safety, deepest wall (dry slope, no tension crack)
A41: Item | B41: Value | C41: Unit | D41: What it means
A42: Slope height, H (deepest wall) | B42: =K26 -> 45.5 | C42: m | D42: Deepest wall on the economic pit outline.
A43: Overall slope angle of that wall, ψf | B43: =IFERROR(INDEX(E6:E25,MATCH(K26,K6:K25,0)),0) -> 43.136306 | C43: degrees | D43: From the bench geometry for that wall.
A44: Unit weight of rock, γ | B44: =Inputs!$B$9*9.81 -> 21.582 | C44: kN/m³ | D44: Overburden density (t/m³) × 9.81.
A45: Cohesion, c | B45: =Inputs!$B$62 -> 30 | C45: kPa
A46: Friction angle, φ | B46: =Inputs!$B$63 -> 30 | C46: degrees
A47: Failure plane dip, ψp | B47: =Inputs!$B$64 -> 35 | C47: degrees | D47: The plane must be flatter than the slope to daylight in the face.
A48: Weight of sliding block, W | B48: =IF(AND(B42>0,B47<B43),0.5*B44*B42^2*(1/TAN(RADIANS(B47))-1/TAN(RADIANS(B43))),0) -> 8062.1075 | C48: kN per m | D48: W = ½ γ H² (cot ψp − cot ψf), per metre of wall length.
A49: Area of failure plane, A | B49: =IF(B42>0,B42/SIN(RADIANS(B47)),0) -> 79.326829 | C49: m² per m | D49: A = H ÷ sin ψp.
A50: Resisting force | B50: =B45*B49+B48*COS(RADIANS(B47))*TAN(RADIANS(B46)) -> 6192.6791 | C50: kN per m | D50: c × A + W cos ψp tan φ.
A51: Driving force | B51: =B48*SIN(RADIANS(B47)) -> 4624.2349 | C51: kN per m | D51: W sin ψp.
A52: Factor of safety, FoS | B52: =IF(B51>0,B50/B51,"No daylight") -> 1.3391792 | C52: ratio | D52: Resisting ÷ driving. Below 1.0 the block slides.
A53: Target factor of safety | B53: =Inputs!$B$65 -> 1.3 | C53: ratio
A54: Verdict | B54: =IF(ISNUMBER(B52),IF(B52>=B53,"Meets target","Below target"),"Stable") -> Meets target | D54: Stable means the failure plane does not daylight in the slope face.
A56: D. Slope-angle trade-off at the same wall height: steeper walls cut stripping but lower the factor of safety
A57: Overall slope angle (degrees) | B57: Factor of safety | C57: Meets target? | D57: Flag | E57: Wedge per metre of wall (BCM/m)
A58: 30 | B58: =IF(OR($B$42=0,A58<=$B$47),"Stable",($B$45*$B$49+0.5*$B$44*$B$42^2*(1/TAN(RADIANS($B$47))-1/TAN(RADIANS(A58)))*COS(RADIANS($B$47))*TAN(RADIANS($B$46)))/(0.5*$B$44*$B$42^2*(1/TAN(RADIANS($B$47))-1/TAN(RADIANS(A58)))*SIN(RADIANS($B$47)))) -> Stable | C58: =IF(ISNUMBER(B58),IF(B58>=$B$53,"Yes","No"),"Yes") -> Yes | D58: =IF(C58="Yes",1,0) -> 1 | E58: =IF($B$42=0,0,0.5*$B$42^2/TAN(RADIANS(A58))) -> 1792.8891
A59: 35 | B59: =IF(OR($B$42=0,A59<=$B$47),"Stable",($B$45*$B$49+0.5*$B$44*$B$42^2*(1/TAN(RADIANS($B$47))-1/TAN(RADIANS(A59)))*COS(RADIANS($B$47))*TAN(RADIANS($B$46)))/(0.5*$B$44*$B$42^2*(1/TAN(RADIANS($B$47))-1/TAN(RADIANS(A59)))*SIN(RADIANS($B$47)))) -> Stable | C59: =IF(ISNUMBER(B59),IF(B59>=$B$53,"Yes","No"),"Yes") -> Yes | D59: =IF(C59="Yes",1,0) -> 1 | E59: =IF($B$42=0,0,0.5*$B$42^2/TAN(RADIANS(A59))) -> 1478.3117
A60: 40 | B60: =IF(OR($B$42=0,A60<=$B$47),"Stable",($B$45*$B$49+0.5*$B$44*$B$42^2*(1/TAN(RADIANS($B$47))-1/TAN(RADIANS(A60)))*COS(RADIANS($B$47))*TAN(RADIANS($B$46)))/(0.5*$B$44*$B$42^2*(1/TAN(RADIANS($B$47))-1/TAN(RADIANS(A60)))*SIN(RADIANS($B$47)))) -> 1.6101903 | C60: =IF(ISNUMBER(B60),IF(B60>=$B$53,"Yes","No"),"Yes") -> Yes | D60: =IF(C60="Yes",1,0) -> 1 | E60: =IF($B$42=0,0,0.5*$B$42^2/TAN(RADIANS(A60))) -> 1233.6139
A61: 45 | B61: =IF(OR($B$42=0,A61<=$B$47),"Stable",($B$45*$B$49+0.5*$B$44*$B$42^2*(1/TAN(RADIANS($B$47))-1/TAN(RADIANS(A61)))*COS(RADIANS($B$47))*TAN(RADIANS($B$46)))/(0.5*$B$44*$B$42^2*(1/TAN(RADIANS($B$47))-1/TAN(RADIANS(A61)))*SIN(RADIANS($B$47)))) -> 1.2583237 | C61: =IF(ISNUMBER(B61),IF(B61>=$B$53,"Yes","No"),"Yes") -> No | D61: =IF(C61="Yes",1,0) -> 0 | E61: =IF($B$42=0,0,0.5*$B$42^2/TAN(RADIANS(A61))) -> 1035.125
A62: 50 | B62: =IF(OR($B$42=0,A62<=$B$47),"Stable",($B$45*$B$49+0.5*$B$44*$B$42^2*(1/TAN(RADIANS($B$47))-1/TAN(RADIANS(A62)))*COS(RADIANS($B$47))*TAN(RADIANS($B$46)))/(0.5*$B$44*$B$42^2*(1/TAN(RADIANS($B$47))-1/TAN(RADIANS(A62)))*SIN(RADIANS($B$47)))) -> 1.1398348 | C62: =IF(ISNUMBER(B62),IF(B62>=$B$53,"Yes","No"),"Yes") -> No | D62: =IF(C62="Yes",1,0) -> 0 | E62: =IF($B$42=0,0,0.5*$B$42^2/TAN(RADIANS(A62))) -> 868.57301
A63: 55 | B63: =IF(OR($B$42=0,A63<=$B$47),"Stable",($B$45*$B$49+0.5*$B$44*$B$42^2*(1/TAN(RADIANS($B$47))-1/TAN(RADIANS(A63)))*COS(RADIANS($B$47))*TAN(RADIANS($B$46)))/(0.5*$B$44*$B$42^2*(1/TAN(RADIANS($B$47))-1/TAN(RADIANS(A63)))*SIN(RADIANS($B$47)))) -> 1.0796764 | C63: =IF(ISNUMBER(B63),IF(B63>=$B$53,"Yes","No"),"Yes") -> No | D63: =IF(C63="Yes",1,0) -> 0 | E63: =IF($B$42=0,0,0.5*$B$42^2/TAN(RADIANS(A63))) -> 724.80233
A64: 60 | B64: =IF(OR($B$42=0,A64<=$B$47),"Stable",($B$45*$B$49+0.5*$B$44*$B$42^2*(1/TAN(RADIANS($B$47))-1/TAN(RADIANS(A64)))*COS(RADIANS($B$47))*TAN(RADIANS($B$46)))/(0.5*$B$44*$B$42^2*(1/TAN(RADIANS($B$47))-1/TAN(RADIANS(A64)))*SIN(RADIANS($B$47)))) -> 1.0428343 | C64: =IF(ISNUMBER(B64),IF(B64>=$B$53,"Yes","No"),"Yes") -> No | D64: =IF(C64="Yes",1,0) -> 0 | E64: =IF($B$42=0,0,0.5*$B$42^2/TAN(RADIANS(A64))) -> 597.6297
A65: 65 | B65: =IF(OR($B$42=0,A65<=$B$47),"Stable",($B$45*$B$49+0.5*$B$44*$B$42^2*(1/TAN(RADIANS($B$47))-1/TAN(RADIANS(A65)))*COS(RADIANS($B$47))*TAN(RADIANS($B$46)))/(0.5*$B$44*$B$42^2*(1/TAN(RADIANS($B$47))-1/TAN(RADIANS(A65)))*SIN(RADIANS($B$47)))) -> 1.0176329 | C65: =IF(ISNUMBER(B65),IF(B65>=$B$53,"Yes","No"),"Yes") -> No | D65: =IF(C65="Yes",1,0) -> 0 | E65: =IF($B$42=0,0,0.5*$B$42^2/TAN(RADIANS(A65))) -> 482.68671
A66: Steepest slope that meets the target FoS | B66: =SUMPRODUCT(MAX(D58:D65*A58:A65)) -> 40 | C66: degrees | D66: Largest angle in the table whose flag is 1.
A67: Slope angle used in the design (deepest wall) | B67: =B43 -> 43.136306 | C67: degrees | D67: If this is above the line above, flatten the slope or add berm width.
A69: E. Haul ramp
A70: Item | B70: Value | C70: Unit | D70: What it means
A71: Ramp gradient | B71: =Inputs!$B$66 -> 8 | C71: %
A72: Deepest economic block floor | B72: =SUMPRODUCT(MAX(B6:B25*C6:C25)) -> 45.5 | C72: m | D72: Depth the ramp must reach.
A73: Ramp length to reach the deepest floor | B73: =IF(B71>0,B72/(B71/100),0) -> 568.75 | C73: m | D73: Depth ÷ gradient. Adds to the haul distance and to the stripping needed for the ramp.
A74: Gradient expressed as 1 in | B74: =IF(B71>0,100/B71,0) -> 12.5

Sheet Fleet
A1: Fleet — how many excavators and dumpers does the target need?
A2: Column B = overburden, column C = coal. Every row is a formula; the note says what it means.
A4: Item | B4: Overburden | C4: Coal | D4: Unit | E4: What it means
A5: A. Excavator productivity
A6: Swell factor (loose ÷ bank) | B6: =Inputs!$B$15 -> 1.35 | C6: =Inputs!$B$16 -> 1.3 | D6: ratio | E6: Pulled from Inputs.
A7: Density in the bank | B7: =Inputs!$B$9 -> 2.2 | C7: =Inputs!$B$8 -> 1.4 | D7: t/m³ | E7: Pulled from Inputs.
A8: Bucket payload per pass | B8: =Inputs!$B$13*Inputs!$B$14/B6 -> 2.5185185 | C8: =Inputs!$B$13*Inputs!$B$14/C6 -> 2.6153846 | D8: BCM | E8: Bucket × fill factor ÷ swell. The loose rock in the bucket, converted back to bank volume.
A9: Bucket payload per pass | B9: =B8*B7 -> 5.5407407 | C9: =C8*C7 -> 3.6615385 | D9: t | E9: Bank volume × density.
A10: Excavator passes per hour | B10: =3600/Inputs!$B$17*Inputs!$B$18/60 -> 100 | C10: =3600/Inputs!$B$17*Inputs!$B$18/60 -> 100 | D10: passes | E10: 3600 s ÷ cycle time gives passes in a full hour; × efficiency (min ÷ 60) gives productive passes.
A11: Excavator productivity | B11: =B8*B10 -> 251.85185 | C11: =C8*C10 -> 261.53846 | D11: BCM/hr | E11: Payload per pass × passes per hour.
A12: Excavator productivity | B12: =B11*B7 -> 554.07407 | C12: =C11*C7 -> 366.15385 | D12: t/hr | E12: BCM/hr × density.
A13: B. Dumper cycle (one trip)
A14: Haul distance one way | B14: =Inputs!$B$21 -> 2 | C14: =Inputs!$B$22 -> 3 | D14: km | E14: Pulled from Inputs.
A15: Buckets needed to load one dumper | B15: =ROUNDDOWN(Inputs!$B$20/B9,0) -> 6 | C15: =ROUNDDOWN(Inputs!$B$20/C9,0) -> 9 | D15: passes | E15: Rated payload ÷ tonnes per bucket, rounded DOWN so the dumper is not overloaded.
A16: Actual payload per trip | B16: =B15*B9 -> 33.244444 | C16: =C15*C9 -> 32.953846 | D16: t | E16: Whole buckets × tonnes per bucket.
A17: Loading time | B17: =B15*Inputs!$B$17/60 -> 3 | C17: =C15*Inputs!$B$17/60 -> 4.5 | D17: min | E17: Buckets × excavator cycle time.
A18: Loaded haul time | B18: =B14/Inputs!$B$23*60 -> 6 | C18: =C14/Inputs!$B$23*60 -> 9 | D18: min | E18: Distance ÷ speed × 60.
A19: Return time, empty | B19: =B14/Inputs!$B$24*60 -> 4.2857143 | C19: =C14/Inputs!$B$24*60 -> 6.4285714 | D19: min | E19: Distance ÷ speed × 60.
A20: Spotting + dumping time | B20: =Inputs!$B$25+Inputs!$B$26 -> 2 | C20: =Inputs!$B$25+Inputs!$B$26 -> 2 | D20: min | E20: Fixed time at each end.
A21: Total dumper cycle time | B21: =B17+B18+B19+B20 -> 15.285714 | C21: =C17+C18+C19+C20 -> 21.928571 | D21: min | E21: Load + haul + return + spot and dump.
A22: Trips per hour | B22: =Inputs!$B$27/B21 -> 3.271028 | C22: =Inputs!$B$27/C21 -> 2.2801303 | D22: trips | E22: Productive minutes per hour ÷ cycle time.
A23: Dumper productivity | B23: =B22*B16 -> 108.74351 | C23: =C22*C16 -> 75.139063 | D23: t/hr | E23: Trips per hour × payload per trip.
A24: Dumpers needed to keep one excavator busy | B24: =B21/B17 -> 5.0952381 | C24: =C21/C17 -> 4.8730159 | D24: dumpers | E24: Cycle time ÷ loading time. This is the fleet match number.
A25: C. Fleet required for the production target
A26: Effective hours per machine per year | B26: =Inputs!$B$29*Inputs!$B$30*Inputs!$B$31*Inputs!$B$32*Inputs!$B$33 -> 5385.6 | D26: hours | E26: Days × shifts × hours × availability × utilisation.
A27: Quantity to move per year | B27: =Inputs!$B$11*Reserve!$B$38 -> 1465542.9 | C27: =Inputs!$B$11/Inputs!$B$8 -> 357142.86 | D27: BCM/yr | E27: Overburden = production × stripping ratio (economic blocks). Coal = production ÷ density.
A28: Quantity to move per year | B28: =B27*B7 -> 3224194.4 | C28: =Inputs!$B$11 -> 500000 | D28: t/yr | E28: Overburden BCM × density. Coal = production target.
A29: Excavator hours needed per year | B29: =B28/B12 -> 5819.0674 | C29: =C28/C12 -> 1365.5462 | D29: hours | E29: Tonnes to move ÷ excavator tonnes per hour.
A30: Dumper hours needed per year | B30: =B28/B23 -> 29649.534 | C30: =C28/C23 -> 6654.3284 | D30: hours | E30: Tonnes to move ÷ dumper tonnes per hour.
A31: Excavators required (overburden + coal) | B31: =ROUNDUP((B29+C29)/B26,0) -> 2 | D31: machines | E31: Total hours needed ÷ hours one machine can work, rounded UP.
A32: Dumpers required (overburden + coal) | B32: =ROUNDUP((B30+C30)/B26,0) -> 7 | D32: machines | E32: Same method for dumpers.
A33: Excavator fleet utilisation | B33: =(B29+C29)/(B31*B26) -> 0.66702072 | D33: % | E33: How busy the rounded-up fleet is. Very low means you may be over-sized.
A34: Dumper fleet utilisation | B34: =(B30+C30)/(B32*B26) -> 0.9629876 | D34: % | E34: Same check for dumpers.
A35: Dumpers per excavator in the fleet | B35: =B32/B31 -> 3.5 | D35: ratio | E35: Compare with the match number above.

Sheet Safety
A1: Safety — blast vibration against DGMS limits, and haul-ramp stopping distance
A2: Ground vibration from the scaled-distance law, and how far a loaded dumper travels before it stops on the ramp. Sample site constants: replace with monitoring data.
A4: A. Blast design
A5: Item | B5: Value | C5: Unit | D5: What it means
A6: Burden, B | B6: =Inputs!$B$92 -> 4 | C6: m
A7: Spacing, S | B7: =Inputs!$B$93 -> 5 | C7: m
A8: Bench height, H | B8: =Inputs!$B$59 -> 10 | C8: m | D8: From the Pit design inputs.
A9: Powder factor | B9: =Inputs!$B$90 -> 0.35 | C9: kg/m³
A10: Rock broken per hole | B10: =B6*B7*B8 -> 200 | C10: BCM | D10: Burden × spacing × height (sub-drilling ignored).
A11: Explosive charge per hole, Q | B11: =B9*B10 -> 70 | C11: kg
A12: Holes firing per delay | B12: =Inputs!$B$94 -> 2 | C12: holes
A13: Maximum charge per delay, Qd | B13: =B11*B12 -> 140 | C13: kg | D13: Controls the ground vibration.
A14: Explosive cost | B14: =Inputs!$B$90*Inputs!$B$91 -> 19.25 | C14: ₹/BCM | D14: Powder factor × cost per kg.
A15: Drilling and blasting cost in the model | B15: =Inputs!$B$35 -> 35 | C15: ₹/BCM | D15: Inputs section 5.
A16: Explosive share of the drilling and blasting cost | B16: =IFERROR(B14/B15,0) -> 0.55 | C16: % | D16: Typically about half. The rest is drilling, accessories and labour.
A18: B. Ground vibration: peak particle velocity (PPV) = K × (R ÷ √Qd)^−β
A19: Item | B19: Value | C19: Unit | D19: What it means
A20: Distance to nearest structure, R | B20: =Inputs!$B$95 -> 300 | C20: m
A21: Site constant K | B21: =Inputs!$B$96 -> 500 | C21: mm/s
A22: Site constant β | B22: =Inputs!$B$97 -> 1.6
A23: Scaled distance, R ÷ √Qd | B23: =B20/SQRT(B13) -> 25.354628 | C23: m/kg^0.5
A24: Predicted PPV | B24: =B21*B23^(-B22) -> 2.8345128 | C24: mm/s
A25: Permissible PPV (DGMS table) | B25: =INDEX($B$34:$D$38,Inputs!$B$98,Inputs!$B$99) -> 10 | C25: mm/s | D25: Looked up from the structure category and frequency band chosen on Inputs.
A26: Status | B26: =IF(B24<=B25,"Within limit","EXCEEDS limit") -> Within limit
A27: Margin: permissible ÷ predicted | B27: =IFERROR(B25/B24,0) -> 3.5279431 | C27: ratio | D27: Above 1 is safe. Aim for a comfortable margin because site constants are uncertain.
A28: Safe distance at this charge | B28: =SQRT(B13)*(B21/B25)^(1/B22) -> 136.43326 | C28: m | D28: Closest a structure can be for the PPV to equal the limit.
A29: Maximum charge per delay at this distance | B29: =(B20/(B21/B25)^(1/B22))^2 -> 676.90856 | C29: kg | D29: Largest Qd that keeps the PPV at the limit. Reduce holes per delay if the status fails.
A31: Permissible PPV by structure and dominant frequency (mm/s)
A32: DGMS (Tech)(S&T) Circular No. 7 of 1997, permissible peak particle velocity at the foundation of structures in mining areas. Verify against the latest circular.
A33: Structure category | B33: Below 8 Hz | C33: 8 to 25 Hz | D33: Above 25 Hz
A34: 1 Domestic houses, not owned by the mine | B34: 5 | C34: 10 | D34: 15
A35: 2 Industrial buildings (RCC and framed), not owned by the mine | B35: 10 | C35: 20 | D35: 25
A36: 3 Historical and sensitive structures | B36: 2 | C36: 5 | D36: 10
A37: 4 Domestic houses, owned by the mine (limited life) | B37: 10 | C37: 15 | D37: 25
A38: 5 Industrial buildings, owned by the mine (limited life) | B38: 15 | C38: 25 | D38: 50
A40: C. Stopping distance for a loaded dumper going down the ramp
A41: Speed (km/h) | B41: Speed (m/s) | C41: Reaction distance (m) | D41: Braking distance (m) | E41: Stopping distance (m) | F41: Within sight distance?
A42: =Inputs!$B$23 -> 20 | B42: =A42/3.6 -> 5.5555556 | C42: =B42*Inputs!$B$100 -> 8.3333333 | D42: =IF(Inputs!$B$101>Inputs!$B$66/100,B42^2/(2*9.81*(Inputs!$B$101-Inputs!$B$66/100)),"cannot stop") -> 5.8262917 | E42: =IF(ISNUMBER(D42),C42+D42,"cannot stop") -> 14.159625 | F42: =IF(ISNUMBER(E42),IF(E42<=Inputs!$B$102,"Yes","No"),"No") -> Yes
A43: =Inputs!$B$103 -> 30 | B43: =A43/3.6 -> 8.3333333 | C43: =B43*Inputs!$B$100 -> 12.5 | D43: =IF(Inputs!$B$101>Inputs!$B$66/100,B43^2/(2*9.81*(Inputs!$B$101-Inputs!$B$66/100)),"cannot stop") -> 13.109156 | E43: =IF(ISNUMBER(D43),C43+D43,"cannot stop") -> 25.609156 | F43: =IF(ISNUMBER(E43),IF(E43<=Inputs!$B$102,"Yes","No"),"No") -> Yes
A44: 10 | B44: =A44/3.6 -> 2.7777778 | C44: =B44*Inputs!$B$100 -> 4.1666667 | D44: =IF(Inputs!$B$101>Inputs!$B$66/100,B44^2/(2*9.81*(Inputs!$B$101-Inputs!$B$66/100)),"cannot stop") -> 1.4565729 | E44: =IF(ISNUMBER(D44),C44+D44,"cannot stop") -> 5.6232396 | F44: =IF(ISNUMBER(E44),IF(E44<=Inputs!$B$102,"Yes","No"),"No") -> Yes
A45: 40 | B45: =A45/3.6 -> 11.111111 | C45: =B45*Inputs!$B$100 -> 16.666667 | D45: =IF(Inputs!$B$101>Inputs!$B$66/100,B45^2/(2*9.81*(Inputs!$B$101-Inputs!$B$66/100)),"cannot stop") -> 23.305167 | E45: =IF(ISNUMBER(D45),C45+D45,"cannot stop") -> 39.971833 | F45: =IF(ISNUMBER(E45),IF(E45<=Inputs!$B$102,"Yes","No"),"No") -> Yes
A46: 50 | B46: =A46/3.6 -> 13.888889 | C46: =B46*Inputs!$B$100 -> 20.833333 | D46: =IF(Inputs!$B$101>Inputs!$B$66/100,B46^2/(2*9.81*(Inputs!$B$101-Inputs!$B$66/100)),"cannot stop") -> 36.414323 | E46: =IF(ISNUMBER(D46),C46+D46,"cannot stop") -> 57.247656 | F46: =IF(ISNUMBER(E46),IF(E46<=Inputs!$B$102,"Yes","No"),"No") -> Yes
A47: Rows 1 and 2 use the average loaded speed and the maximum downhill speed from Inputs; rows 3 to 5 are test speeds.
A48: Braking distance = v² ÷ (2 g (μ − G)) on a downgrade G. Reaction distance = v × reaction time. Compare the total with the sight distance available on the ramp.

Sheet Quality and royalty
A1: Quality and royalty — washability, washing economics and statutory levies
A2: Float-and-sink data give the yield at a target ash. Royalty, DMF and NMET replace the flat levy placeholder. SAMPLE DATA: replace the yellow cells with your own float-sink test.
A4: A. Float-and-sink (washability) data for the run-of-mine coal
A5: Density fraction | B5: Upper density (SG) | C5: Weight (%) | D5: Ash (%) | E5: Cumulative float yield (%) | F5: Cumulative float ash (%) | G5: Ash contribution (% of total)
A6: Float 1.3 | B6: 1.3 | C6: 6 | D6: 8 | E6: =SUM($C$6:C6) -> 6 | F6: =SUM($G$6:G6)/E6*100 -> 8 | G6: =C6*D6/100 -> 0.48
A7: 1.3 – 1.4 | B7: 1.4 | C7: 12 | D7: 14 | E7: =SUM($C$6:C7) -> 18 | F7: =SUM($G$6:G7)/E7*100 -> 12 | G7: =C7*D7/100 -> 1.68
A8: 1.4 – 1.5 | B8: 1.5 | C8: 14 | D8: 22 | E8: =SUM($C$6:C8) -> 32 | F8: =SUM($G$6:G8)/E8*100 -> 16.375 | G8: =C8*D8/100 -> 3.08
A9: 1.5 – 1.6 | B9: 1.6 | C9: 13 | D9: 32 | E9: =SUM($C$6:C9) -> 45 | F9: =SUM($G$6:G9)/E9*100 -> 20.888889 | G9: =C9*D9/100 -> 4.16
A10: 1.6 – 1.8 | B10: 1.8 | C10: 15 | D10: 44 | E10: =SUM($C$6:C10) -> 60 | F10: =SUM($G$6:G10)/E10*100 -> 26.666667 | G10: =C10*D10/100 -> 6.6
A11: 1.8 – 2.0 | B11: 2 | C11: 12 | D11: 58 | E11: =SUM($C$6:C11) -> 72 | F11: =SUM($G$6:G11)/E11*100 -> 31.888889 | G11: =C11*D11/100 -> 6.96
A12: Sink 2.0 | B12: — | C12: 28 | D12: 78 | E12: =SUM($C$6:C12) -> 100 | F12: =SUM($G$6:G12)/E12*100 -> 44.8 | G12: =C12*D12/100 -> 21.84
A13: Total | C13: =SUM(C6:C12) -> 100 | F13: =F12 -> 44.8 | G13: =SUM(G6:G12) -> 44.8
A14: Weights must total 100 %. Cumulative float ash = Σ(weight × ash) ÷ cumulative yield. The last row's cumulative ash is the run-of-mine ash.
A16: B. Washing result at the target ash
A17: Item | B17: Value | C17: Unit | D17: What it means
A18: Target clean-coal ash | B18: =Inputs!$B$71 -> 28 | C18: % | D18: Set on Inputs.
A19: Run-of-mine (raw) ash | B19: =F12 -> 44.8 | C19: %
A20: Position on the washability curve | B20: =IFERROR(MATCH(B18,$F$6:$F$12,1),0) -> 5 | C20: index | D20: Last float-sink row whose cumulative ash is at or below the target.
A21: Interpolation fraction | B21: =IF(AND(B20>=1,B20<=6),(B18-INDEX($F$6:$F$12,B20))/(INDEX($F$6:$F$12,B20+1)-INDEX($F$6:$F$12,B20)),0) -> 0.25531915 | D21: Position between two points of the cumulative curve.
A22: Theoretical yield at the target ash | B22: =IF(B20=0,0,IF(B20>=7,100,INDEX($E$6:$E$12,B20)+B21*(INDEX($E$6:$E$12,B20+1)-INDEX($E$6:$E$12,B20)))) -> 63.06383 | C22: % | D22: Yield of a perfect separation, read off the washability curve.
A23: Cut-point density | B23: =IF(AND(B20>=1,B20<=5),INDEX($B$6:$B$12,B20)+B21*(INDEX($B$6:$B$12,B20+1)-INDEX($B$6:$B$12,B20)),"n/a") -> 1.8510638 | C23: SG | D23: Density at which the washery separates clean coal from reject.
A24: Near-gravity material, cut-point ± 0.1 SG | B24: =IFERROR((INDEX($E$6:$E$11,MATCH((B23+0.1),$B$6:$B$11,1))+((B23+0.1)-INDEX($B$6:$B$11,MATCH((B23+0.1),$B$6:$B$11,1)))/(INDEX($B$6:$B$11,MATCH((B23+0.1),$B$6:$B$11,1)+1)-INDEX($B$6:$B$11,MATCH((B23+0.1),$B$6:$B$11,1)))*(INDEX($E$6:$E$11,MATCH((B23+0.1),$B$6:$B$11,1)+1)-INDEX($E$6:$E$11,MATCH((B23+0.1),$B$6:$B$11,1))))-(INDEX($E$6:$E$11,MATCH((B23-0.1),$B$6:$B$11,1))+((B23-0.1)-INDEX($B$6:$B$11,MATCH((B23-0.1),$B$6:$B$11,1)))/(INDEX($B$6:$B$11,MATCH((B23-0.1),$B$6:$B$11,1)+1)-INDEX($B$6:$B$11,MATCH((B23-0.1),$B$6:$B$11,1)))*(INDEX($E$6:$E$11,MATCH((B23-0.1),$B$6:$B$11,1)+1)-INDEX($E$6:$E$11,MATCH((B23-0.1),$B$6:$B$11,1)))),"n/a") -> 12.734043 | C24: % | D24: Material close to the cut density. More of it means harder separation and lower efficiency.
A25: Organic efficiency | B25: =Inputs!$B$72 -> 0.94 | C25: fraction | D25: Actual yield ÷ theoretical yield at the same ash.
A26: Actual yield at the target ash | B26: =B25*B22 -> 59.28 | C26: %
A27: Reject ash | B27: =IF(B26<100,(B19-B26/100*B18)/(1-B26/100),0) -> 69.257367 | C27: % | D27: Mass balance on ash: feed = clean + reject.
A29: C. Revenue per tonne of run-of-mine coal: wash or sell raw?
A30: Item | B30: Value | C30: Unit | D30: What it means
A31: Raw coal price | B31: =Inputs!$B$42 -> 2200 | C31: ₹/t | D31: Selling price in Inputs section 5.
A32: Washed coal price | B32: =Inputs!$B$73 -> 4200 | C32: ₹/t
A33: Washed yield (fraction of feed) | B33: =B26/100 -> 0.5928
A34: Revenue from washed coal, per tonne of feed | B34: =B33*B32 -> 2489.76 | C34: ₹/t | D34: Yield × washed price.
A35: Value of rejects, per tonne of feed | B35: =(1-B33)*Inputs!$B$75 -> 0 | C35: ₹/t
A36: Less: washing cost | B36: =Inputs!$B$74 -> 150 | C36: ₹/t
A37: Net realisation per tonne of ROM coal | B37: =B34+B35-B36 -> 2339.76 | C37: ₹/t
A38: Benefit of washing over selling raw | B38: =B37-B31 -> 139.76 | C38: ₹/t | D38: Positive means washing pays.
A39: Break-even washed coal price | B39: =IFERROR((B31+B36-B35)/B33,0) -> 3964.2375 | C39: ₹/t | D39: The washed price at which washing and selling raw earn the same.
A40: Verdict | B40: =IF(B38>0,"Washing pays","Sell raw") -> Washing pays
A41: Selling price used in the model, per tonne of ROM | B41: =IF(Inputs!$B$48=1,B37,B31) -> 2200 | C41: ₹/t | D41: Feeds Economics (coal selling price). Switch on Inputs section 6.
A43: D. Statutory levies on coal (mining legislation)
A44: Item | B44: Value | C44: Unit | D44: What it means
A45: Price basis for royalty | B45: =B41 -> 2200 | C45: ₹/t | D45: Royalty is charged on the price of coal. The selling price is used here as a proxy for the notified basic price.
A46: Royalty rate | B46: =Inputs!$B$76 -> 0.14 | C46: ad valorem
A47: Royalty | B47: =B46*B45 -> 308 | C47: ₹/t | D47: Rate × price.
A48: District Mineral Foundation (DMF) | B48: =Inputs!$B$77*B47 -> 92.4 | C48: ₹/t | D48: Percentage of royalty, paid to the district fund.
A49: National Mineral Exploration Trust (NMET) | B49: =Inputs!$B$78*B47 -> 9.24 | C49: ₹/t | D49: Percentage of royalty, paid to the exploration trust.
A50: Other statutory levies | B50: =Inputs!$B$79 -> 10 | C50: ₹/t | D50: Placeholder: check current notifications.
A51: Total statutory levies, built up | B51: =SUM(B47:B50) -> 419.64 | C51: ₹/t
A52: Flat placeholder (Inputs section 5) | B52: =Inputs!$B$41 -> 900 | C52: ₹/t | D52: The original single-number assumption.
A53: Statutory levies used in the model | B53: =IF(Inputs!$B$47=1,B51,B52) -> 900 | C53: ₹/t | D53: Feeds Economics (royalty and levies). Switch on Inputs section 6.
A54: Share of selling price | B54: =IFERROR(B53/B45,0) -> 0.40909091 | C54: %
A55: Annual royalty | B55: =B47*Inputs!$B$11/10000000 -> 15.4 | C55: ₹ crore | D55: At the production target.
A56: Annual DMF + NMET | B56: =(B48+B49)*Inputs!$B$11/10000000 -> 5.082 | C56: ₹ crore
A57: Effective ad valorem rate, royalty + DMF + NMET | B57: =B46*(1+Inputs!$B$77+Inputs!$B$78) -> 0.1862 | C57: of price | D57: Used by the Sensitivity sheet so levies move with the price.
A59: Sources: royalty 14 % ad valorem on coal, MMDR Act 1957 Second Schedule (notified by GSR 349(E), 10 May 2012; Ministry of Coal replies in Parliament, 2020 and draft notification, 2023).
A60: DMF is 30 % of royalty for mining leases granted before 12 January 2015 and 10 % for leases granted on or after that date (Ministry of Coal, Lok Sabha reply of 11 March 2020).
A61: NMET at 2 % of royalty and the other-levy placeholder were not re-verified here. Check the latest notifications. GST on coal and the former compensation cess are not mine costs and are excluded.

Sheet Economics
A1: Economics — cost per tonne, break-even stripping ratio, project value
A2: Costs per unit = machine cost per hour ÷ what the machine produces per hour. Simplified: before tax, constant average stripping ratio.
A4: Item | B4: Value | C4: Unit | D4: What it means
A5: A. Overburden removal cost
A6: Drilling and blasting | B6: =Inputs!$B$35 -> 35 | C6: ₹/BCM | D6: From Inputs.
A7: Excavation | B7: =Inputs!$B$37/Fleet!$B$11 -> 17.867647 | C7: ₹/BCM | D7: Excavator cost per hour ÷ BCM it moves per hour.
A8: Haulage | B8: =Inputs!$B$38/(Fleet!$B$23/Inputs!$B$9) -> 60.693277 | C8: ₹/BCM | D8: Dumper cost per hour ÷ BCM it hauls per hour (tonnes per hour ÷ density).
A9: Overburden removal cost | B9: =SUM(B6:B8) -> 113.56092 | C9: ₹/BCM | D9: Sum of the three above.
A10: B. Coal winning cost (excluding overburden)
A11: Drilling and blasting | B11: =Inputs!$B$36 -> 20 | C11: ₹/t | D11: From Inputs.
A12: Excavation | B12: =Inputs!$B$37/Fleet!$C$12 -> 12.289916 | C12: ₹/t | D12: Excavator cost per hour ÷ coal tonnes per hour.
A13: Haulage | B13: =Inputs!$B$38/Fleet!$C$23 -> 39.92597 | C13: ₹/t | D13: Dumper cost per hour ÷ coal tonnes per hour.
A14: Handling and dispatch | B14: =Inputs!$B$39 -> 150 | C14: ₹/t | D14: From Inputs.
A15: Overheads and site costs | B15: =Inputs!$B$40 -> 600 | C15: ₹/t | D15: From Inputs.
A16: Royalty and levies | B16: ='Quality and royalty'!$B$53 -> 900 | C16: ₹/t | D16: From the Quality and royalty sheet: royalty + DMF + NMET + other levies, or the flat placeholder if the switch on Inputs is 0.
A17: Coal winning cost | B17: =SUM(B11:B16) -> 1722.2159 | C17: ₹/t | D17: Sum of the six lines above.
A18: C. Break-even stripping ratio (the key planning number)
A19: Coal selling price | B19: ='Quality and royalty'!$B$41 -> 2200 | C19: ₹/t | D19: From the Quality and royalty sheet: raw selling price, or net realisation per tonne of ROM coal if washed coal is selected on Inputs.
A20: Margin available to pay for overburden removal | B20: =B19-B17 -> 477.78411 | C20: ₹/t | D20: Price minus coal winning cost.
A21: Break-even stripping ratio | B21: =IF(B9>0,B20/B9,0) -> 4.2072933 | C21: m³/t | D21: Margin ÷ overburden cost per BCM. A block with a higher stripping ratio loses money.
A22: Actual stripping ratio, economic blocks | B22: =Reserve!$B$38 -> 2.9310858 | C22: m³/t | D22: From the Reserve sheet. Includes the pit-slope wedge when the switch on Inputs is 1.
A23: Verdict at the average stripping ratio | B23: =IF(B22<=B21,"Viable on average","Not viable on average") -> Viable on average | D23: Compares actual with break-even.
A24: D. Cost, profit and project value
A25: All-in cost per tonne of coal | B25: =B17+B22*B9 -> 2055.0727 | C25: ₹/t | D25: Coal winning cost + stripping ratio × overburden cost.
A26: Profit per tonne | B26: =B19-B25 -> 144.9273 | C26: ₹/t | D26: Price minus all-in cost (before tax).
A27: Profit margin | B27: =IF(B19>0,B26/B19,0) -> 0.065876046 | C27: % | D27: Profit ÷ price.
A28: Annual production | B28: =Inputs!$B$11 -> 500000 | C28: t/yr | D28: From Inputs.
A29: Annual revenue | B29: =B28*B19/10000000 -> 110 | C29: ₹ crore | D29: 1 crore = 10,000,000.
A30: Annual cost | B30: =B28*B25/10000000 -> 102.75363 | C30: ₹ crore
A31: Annual profit before tax | B31: =B29-B30 -> 7.246365 | C31: ₹ crore
A32: Mine life (economic blocks) | B32: =Reserve!$B$40 -> 3.38744 | C32: years | D32: From the Reserve sheet.
A33: Non-equipment capital cost | B33: =Inputs!$B$43 -> 10 | C33: ₹ crore | D33: From Inputs.
A34: Net present value (NPV) | B34: ='Cash flow'!$B$19 -> 9.9382192 | C34: ₹ crore | D34: From the Cash flow sheet. Positive means the project earns more than the discount rate.

Sheet Cash flow
A1: Cash flow — year by year over the mine life
A2: Production each year = the smaller of the annual target and the coal still left. Profit is discounted back to today's value.
A4: Year | B4: Opening reserve (t) | C4: Production (t) | D4: Closing reserve (t) | E4: Revenue (₹ crore) | F4: Cost (₹ crore) | G4: Cash flow (₹ crore) | H4: Discount factor | I4: Present value (₹ crore)
A5: 1 | B5: =Reserve!$B$39 -> 1693720 | C5: =MIN(Inputs!$B$11,B5) -> 500000 | D5: =B5-C5 -> 1193720 | E5: =C5*Economics!$B$19/10000000 -> 110 | F5: =C5*Economics!$B$25/10000000 -> 102.75363 | G5: =E5-F5 -> 7.246365 | H5: =1/(1+Inputs!$B$44)^A5 -> 0.90909091 | I5: =G5*H5 -> 6.5876046
A6: 2 | B6: =D5 -> 1193720 | C6: =MIN(Inputs!$B$11,B6) -> 500000 | D6: =B6-C6 -> 693720 | E6: =C6*Economics!$B$19/10000000 -> 110 | F6: =C6*Economics!$B$25/10000000 -> 102.75363 | G6: =E6-F6 -> 7.246365 | H6: =1/(1+Inputs!$B$44)^A6 -> 0.82644628 | I6: =G6*H6 -> 5.9887314
A7: 3 | B7: =D6 -> 693720 | C7: =MIN(Inputs!$B$11,B7) -> 500000 | D7: =B7-C7 -> 193720 | E7: =C7*Economics!$B$19/10000000 -> 110 | F7: =C7*Economics!$B$25/10000000 -> 102.75363 | G7: =E7-F7 -> 7.246365 | H7: =1/(1+Inputs!$B$44)^A7 -> 0.7513148 | I7: =G7*H7 -> 5.4443013
A8: 4 | B8: =D7 -> 193720 | C8: =MIN(Inputs!$B$11,B8) -> 193720 | D8: =B8-C8 -> 0 | E8: =C8*Economics!$B$19/10000000 -> 42.6184 | F8: =C8*Economics!$B$25/10000000 -> 39.810868 | G8: =E8-F8 -> 2.8075317 | H8: =1/(1+Inputs!$B$44)^A8 -> 0.68301346 | I8: =G8*H8 -> 1.9175819
A9: 5 | B9: =D8 -> 0 | C9: =MIN(Inputs!$B$11,B9) -> 0 | D9: =B9-C9 -> 0 | E9: =C9*Economics!$B$19/10000000 -> 0 | F9: =C9*Economics!$B$25/10000000 -> 0 | G9: =E9-F9 -> 0 | H9: =1/(1+Inputs!$B$44)^A9 -> 0.62092132 | I9: =G9*H9 -> 0
A10: 6 | B10: =D9 -> 0 | C10: =MIN(Inputs!$B$11,B10) -> 0 | D10: =B10-C10 -> 0 | E10: =C10*Economics!$B$19/10000000 -> 0 | F10: =C10*Economics!$B$25/10000000 -> 0 | G10: =E10-F10 -> 0 | H10: =1/(1+Inputs!$B$44)^A10 -> 0.56447393 | I10: =G10*H10 -> 0
A11: 7 | B11: =D10 -> 0 | C11: =MIN(Inputs!$B$11,B11) -> 0 | D11: =B11-C11 -> 0 | E11: =C11*Economics!$B$19/10000000 -> 0 | F11: =C11*Economics!$B$25/10000000 -> 0 | G11: =E11-F11 -> 0 | H11: =1/(1+Inputs!$B$44)^A11 -> 0.51315812 | I11: =G11*H11 -> 0
A12: 8 | B12: =D11 -> 0 | C12: =MIN(Inputs!$B$11,B12) -> 0 | D12: =B12-C12 -> 0 | E12: =C12*Economics!$B$19/10000000 -> 0 | F12: =C12*Economics!$B$25/10000000 -> 0 | G12: =E12-F12 -> 0 | H12: =1/(1+Inputs!$B$44)^A12 -> 0.46650738 | I12: =G12*H12 -> 0
A13: 9 | B13: =D12 -> 0 | C13: =MIN(Inputs!$B$11,B13) -> 0 | D13: =B13-C13 -> 0 | E13: =C13*Economics!$B$19/10000000 -> 0 | F13: =C13*Economics!$B$25/10000000 -> 0 | G13: =E13-F13 -> 0 | H13: =1/(1+Inputs!$B$44)^A13 -> 0.42409762 | I13: =G13*H13 -> 0
A14: 10 | B14: =D13 -> 0 | C14: =MIN(Inputs!$B$11,B14) -> 0 | D14: =B14-C14 -> 0 | E14: =C14*Economics!$B$19/10000000 -> 0 | F14: =C14*Economics!$B$25/10000000 -> 0 | G14: =E14-F14 -> 0 | H14: =1/(1+Inputs!$B$44)^A14 -> 0.38554329 | I14: =G14*H14 -> 0
A15: Total | C15: =SUM(C5:C14) -> 1693720 | E15: =SUM(E5:E14) -> 372.6184 | F15: =SUM(F5:F14) -> 348.07177 | G15: =SUM(G5:G14) -> 24.546627 | I15: =SUM(I5:I14) -> 19.938219
A17: Sum of present values (₹ crore) | B17: =I15 -> 19.938219
A18: Less: non-equipment capital cost (₹ crore) | B18: =Inputs!$B$43 -> 10
A19: Net present value, NPV (₹ crore) | B19: =B17-B18 -> 9.9382192
A20: If the mine life is longer than 10 years, extend the table by copying the last row down.

Sheet Mine planning
A1: Mine planning — Taylor's rule, effective cut-off stripping ratio and daily material movement
A2: Is the production target sensible for the reserve? Does the pit-slope burden change which blocks are worth mining? How much must move each day?
A4: A. Taylor's rule for mine life and production rate
A5: Item | B5: Value | C5: Unit | D5: What it means
A6: Recoverable reserve, economic blocks | B6: =Reserve!B39/1000000 -> 1.69372 | C6: million t | D6: From the Reserve sheet.
A7: Taylor mine life, T = 0.2 × (reserve in tonnes)^0.25 | B7: =Inputs!$B$68*(B6*1000000)^Inputs!$B$69 -> 7.2150675 | C7: years | D7: Empirical rule from metal mines (about ±25 %). Treat it as a sense-check, not a design.
A8: Taylor optimum production rate | B8: =IF(B7>0,B6/B7,0) -> 0.23474763 | C8: million t/yr | D8: Reserve ÷ Taylor life.
A9: Range for life + 25 % (slower) | B9: =IF(B7>0,B6/(B7*1.25),0) -> 0.1877981 | C9: million t/yr | D9: Lower end of the acceptable production range.
A10: Range for life − 25 % (faster) | B10: =IF(B7>0,B6/(B7*0.75),0) -> 0.31299684 | C10: million t/yr | D10: Upper end of the acceptable production range.
A11: Your production target | B11: =Inputs!$B$11/1000000 -> 0.5 | C11: million t/yr | D11: Inputs section 1.
A12: Your mine life | B12: =Reserve!B40 -> 3.38744 | C12: years
A13: Target ÷ Taylor optimum | B13: =IFERROR(B11/B8,0) -> 2.129947 | C13: ratio
A14: Verdict | B14: =IF(B11>B10,"Above range",IF(B11<B9,"Below range","Within range")) -> Above range | D14: Above range: fast, capital-heavy and short-lived. Below range: slow and long-lived.
A16: B. Fleet implied by your target and by the Taylor rate
A17: Item | B17: Your target | C17: Taylor optimum | D17: What it means
A18: Coal production | B18: =Inputs!$B$11 -> 500000 | C18: =B8*1000000 -> 234747.63 | D18: t/yr
A19: Mine life | B19: =B12 -> 3.38744 | C19: =B7 -> 7.2150675 | D19: years
A20: Excavator hours needed per year | B20: =Fleet!B29+Fleet!C29 -> 7184.6136 | C20: =B20*C18/B18 -> 3373.142 | D20: Scaled in proportion to production.
A21: Excavators required | B21: =ROUNDUP(B20/Fleet!$B$26,0) -> 2 | C21: =ROUNDUP(C20/Fleet!$B$26,0) -> 1 | D21: machines
A22: Dumper hours needed per year | B22: =Fleet!B30+Fleet!C30 -> 36303.862 | C22: =B22*C18/B18 -> 17044.491 | D22: Scaled in proportion to production.
A23: Dumpers required | B23: =ROUNDUP(B22/Fleet!$B$26,0) -> 7 | C23: =ROUNDUP(C22/Fleet!$B$26,0) -> 4 | D23: machines
A24: Equipment capital | B24: =B21*Inputs!$B$81+B23*Inputs!$B$82 -> 22 | C24: =C21*Inputs!$B$81+C23*Inputs!$B$82 -> 12 | D24: ₹ crore. A faster rate needs more machines up front but pays back sooner.
A26: C. Effective cut-off stripping ratio: break-even less the pit-slope burden
A27: Item | B27: Value | C27: Unit | D27: What it means
A28: Break-even stripping ratio | B28: =Economics!B21 -> 4.2072933 | C28: m³/t | D28: A block above this loses money on its own overburden.
A29: Pit-slope burden on the stripping ratio | B29: ='Pit design'!$B$37-'Pit design'!$B$36 -> 0.58453501 | C29: m³/t | D29: Extra wall rock spread over the economic coal. Zero if the wedge switch is off.
A30: Effective cut-off stripping ratio | B30: =B28-B29 -> 3.6227583 | C30: m³/t | D30: What is left for a block's own overburden once the walls are paid for.
A31: Blocks at or below break-even | B31: =COUNTIF(Reserve!$H$6:$H$25,"<="&B28) -> 16 | C31: blocks | D31: Block-only test used on the Reserve sheet.
A32: Blocks at or below the effective cut-off | B32: =COUNTIF(Reserve!$H$6:$H$25,"<="&B30) -> 15 | C32: blocks | D32: Stricter test. If lower, re-run the pit limit: marginal blocks cannot carry the wall rock.
A33: Blocks that are marginal | B33: =B31-B32 -> 1 | C33: blocks
A35: D. Daily material movement for the target
A36: Item | B36: Value | C36: Unit | D36: What it means
A37: Coal to produce per working day | B37: =Inputs!$B$11/Inputs!$B$29 -> 1515.1515 | C37: t/day
A38: Overburden to remove per working day | B38: =Fleet!B27/Inputs!$B$29 -> 4441.0391 | C38: BCM/day | D38: From the Fleet sheet quantity, including the pit-slope wedge.
A39: Overburden per shift | B39: =B38/Inputs!$B$30 -> 1480.3464 | C39: BCM/shift
A40: Total material moved per working day | B40: =(Fleet!B28+Fleet!C28)/Inputs!$B$29 -> 11285.438 | C40: t/day | D40: Overburden plus coal, in tonnes.

Sheet Finance
A1: Finance — depreciation, tax, post-tax NPV, IRR and payback
A2: Equipment capital is explicit here, so ownership cost is removed from cash cost and replaced by depreciation. Before tax, this differs from the Cash flow sheet, which keeps ownership inside the hourly rates.
A4: A. Capital, cash cost and settings
A5: Item | B5: Value | C5: Unit | D5: What it means
A6: Excavators required | B6: =Fleet!B31 -> 2 | C6: machines | D6: From the Fleet sheet.
A7: Dumpers required | B7: =Fleet!B32 -> 7 | C7: machines
A8: Excavator price, each | B8: =Inputs!$B$81 -> 4 | C8: ₹ crore
A9: Dumper price, each | B9: =Inputs!$B$82 -> 2 | C9: ₹ crore
A10: Equipment capital | B10: =B6*B8+B7*B9 -> 22 | C10: ₹ crore | D10: Depreciable base.
A11: Non-equipment capital | B11: =Inputs!$B$43 -> 10 | C11: ₹ crore | D11: Land, roads, infrastructure, clearances. Not depreciated here.
A12: Total capital at year 0 | B12: =B10+B11 -> 32 | C12: ₹ crore
A13: Ownership share of machine hourly cost | B13: =Inputs!$B$83 -> 0.25 | C13: fraction
A14: Ownership cost inside the all-in cost | B14: =B13*(Economics!B22*(Economics!B7+Economics!B8)+Economics!B12+Economics!B13) -> 70.621174 | C14: ₹/t | D14: Share × machine cost (excavation + haulage) of overburden and coal per tonne.
A15: All-in cost per tonne (Economics) | B15: =Economics!B25 -> 2055.0727 | C15: ₹/t
A16: Cash operating cost per tonne | B16: =B15-B14 -> 1984.4515 | C16: ₹/t | D16: All-in cost without ownership: capital and depreciation are handled below.
A17: Closure year | B17: =ROUNDUP(Reserve!B40,0) -> 4 | C17: year | D17: Mine life rounded up. Equipment is sold at the end of this year.
A18: Depreciation method | B18: =Inputs!$B$84 -> 1 | C18: =CHOOSE(B18,"Straight line","Written-down value","Units of production") -> Straight line | D18: 1 = straight line, 2 = written-down value, 3 = units of production.
A19: Tax rate | B19: =Inputs!$B$88 -> 0.25 | D19: Placeholder: set the current rate on Inputs.
A20: Discount rate | B20: =Inputs!$B$44 -> 0.1
A22: B. Year-by-year cash flow after depreciation and tax (₹ crore, except production in tonnes)
A23: Year | B23: Production (t) | C23: Revenue | D23: Cash operating cost | E23: EBITDA | F23: Opening book value | G23: Depreciation | H23: Closing book value | I23: Equipment sale proceeds | J23: Loss on sale | K23: Taxable profit | L23: Tax | M23: Capital spend | N23: Pre-tax cash flow | O23: Post-tax cash flow | P23: Discount factor | Q23: PV of post-tax cash flow | R23: Cumulative post-tax cash flow | S23: Payback helper
A24: 0 | M24: =B12 -> 32 | N24: =-M24 -> -32 | O24: =-M24 -> -32 | P24: =1/(1+$B$20)^A24 -> 1 | Q24: =O24*P24 -> -32 | R24: =O24 -> -32
A25: 1 | B25: ='Cash flow'!C5 -> 500000 | C25: =B25*Economics!$B$19/10000000 -> 110 | D25: =B25*$B$16/10000000 -> 99.222576 | E25: =C25-D25 -> 10.777424 | F25: =IF(A25>$B$17,0,IF(A25=1,$B$10,H24)) -> 22 | G25: =IF(A25>$B$17,0,CHOOSE($B$18,MIN(F25,$B$10/Inputs!$B$85),F25*Inputs!$B$86,IFERROR($B$10*B25/SUM($B$25:$B$34),0))) -> 2.75 | H25: =F25-G25 -> 19.25 | I25: =IF(A25=$B$17,Inputs!$B$87*H25,0) -> 0 | J25: =IF(A25=$B$17,H25-I25,0) -> 0 | K25: =E25-G25-J25 -> 8.0274237 | L25: =MAX(0,K25)*$B$19 -> 2.0068559 | N25: =E25+I25 -> 10.777424 | O25: =E25-L25+I25 -> 8.7705678 | P25: =1/(1+$B$20)^A25 -> 0.90909091 | Q25: =O25*P25 -> 7.9732435 | R25: =R24+O25 -> -23.229432 | S25: =IF(AND(R24<0,R25>=0),(A25-1)+(-R24)/O25,"")
A26: 2 | B26: ='Cash flow'!C6 -> 500000 | C26: =B26*Economics!$B$19/10000000 -> 110 | D26: =B26*$B$16/10000000 -> 99.222576 | E26: =C26-D26 -> 10.777424 | F26: =IF(A26>$B$17,0,IF(A26=1,$B$10,H25)) -> 19.25 | G26: =IF(A26>$B$17,0,CHOOSE($B$18,MIN(F26,$B$10/Inputs!$B$85),F26*Inputs!$B$86,IFERROR($B$10*B26/SUM($B$25:$B$34),0))) -> 2.75 | H26: =F26-G26 -> 16.5 | I26: =IF(A26=$B$17,Inputs!$B$87*H26,0) -> 0 | J26: =IF(A26=$B$17,H26-I26,0) -> 0 | K26: =E26-G26-J26 -> 8.0274237 | L26: =MAX(0,K26)*$B$19 -> 2.0068559 | N26: =E26+I26 -> 10.777424 | O26: =E26-L26+I26 -> 8.7705678 | P26: =1/(1+$B$20)^A26 -> 0.82644628 | Q26: =O26*P26 -> 7.2484031 | R26: =R25+O26 -> -14.458864 | S26: =IF(AND(R25<0,R26>=0),(A26-1)+(-R25)/O26,"")
A27: 3 | B27: ='Cash flow'!C7 -> 500000 | C27: =B27*Economics!$B$19/10000000 -> 110 | D27: =B27*$B$16/10000000 -> 99.222576 | E27: =C27-D27 -> 10.777424 | F27: =IF(A27>$B$17,0,IF(A27=1,$B$10,H26)) -> 16.5 | G27: =IF(A27>$B$17,0,CHOOSE($B$18,MIN(F27,$B$10/Inputs!$B$85),F27*Inputs!$B$86,IFERROR($B$10*B27/SUM($B$25:$B$34),0))) -> 2.75 | H27: =F27-G27 -> 13.75 | I27: =IF(A27=$B$17,Inputs!$B$87*H27,0) -> 0 | J27: =IF(A27=$B$17,H27-I27,0) -> 0 | K27: =E27-G27-J27 -> 8.0274237 | L27: =MAX(0,K27)*$B$19 -> 2.0068559 | N27: =E27+I27 -> 10.777424 | O27: =E27-L27+I27 -> 8.7705678 | P27: =1/(1+$B$20)^A27 -> 0.7513148 | Q27: =O27*P27 -> 6.5894574 | R27: =R26+O27 -> -5.6882966 | S27: =IF(AND(R26<0,R27>=0),(A27-1)+(-R26)/O27,"")
A28: 4 | B28: ='Cash flow'!C8 -> 193720 | C28: =B28*Economics!$B$19/10000000 -> 42.6184 | D28: =B28*$B$16/10000000 -> 38.442795 | E28: =C28-D28 -> 4.1756051 | F28: =IF(A28>$B$17,0,IF(A28=1,$B$10,H27)) -> 13.75 | G28: =IF(A28>$B$17,0,CHOOSE($B$18,MIN(F28,$B$10/Inputs!$B$85),F28*Inputs!$B$86,IFERROR($B$10*B28/SUM($B$25:$B$34),0))) -> 2.75 | H28: =F28-G28 -> 11 | I28: =IF(A28=$B$17,Inputs!$B$87*H28,0) -> 5.5 | J28: =IF(A28=$B$17,H28-I28,0) -> 5.5 | K28: =E28-G28-J28 -> -4.0743949 | L28: =MAX(0,K28)*$B$19 -> 0 | N28: =E28+I28 -> 9.6756051 | O28: =E28-L28+I28 -> 9.6756051 | P28: =1/(1+$B$20)^A28 -> 0.68301346 | Q28: =O28*P28 -> 6.6085684 | R28: =R27+O28 -> 3.9873084 | S28: =IF(AND(R27<0,R28>=0),(A28-1)+(-R27)/O28,"") -> 3.5879009
A29: 5 | B29: ='Cash flow'!C9 -> 0 | C29: =B29*Economics!$B$19/10000000 -> 0 | D29: =B29*$B$16/10000000 -> 0 | E29: =C29-D29 -> 0 | F29: =IF(A29>$B$17,0,IF(A29=1,$B$10,H28)) -> 0 | G29: =IF(A29>$B$17,0,CHOOSE($B$18,MIN(F29,$B$10/Inputs!$B$85),F29*Inputs!$B$86,IFERROR($B$10*B29/SUM($B$25:$B$34),0))) -> 0 | H29: =F29-G29 -> 0 | I29: =IF(A29=$B$17,Inputs!$B$87*H29,0) -> 0 | J29: =IF(A29=$B$17,H29-I29,0) -> 0 | K29: =E29-G29-J29 -> 0 | L29: =MAX(0,K29)*$B$19 -> 0 | N29: =E29+I29 -> 0 | O29: =E29-L29+I29 -> 0 | P29: =1/(1+$B$20)^A29 -> 0.62092132 | Q29: =O29*P29 -> 0 | R29: =R28+O29 -> 3.9873084 | S29: =IF(AND(R28<0,R29>=0),(A29-1)+(-R28)/O29,"")
A30: 6 | B30: ='Cash flow'!C10 -> 0 | C30: =B30*Economics!$B$19/10000000 -> 0 | D30: =B30*$B$16/10000000 -> 0 | E30: =C30-D30 -> 0 | F30: =IF(A30>$B$17,0,IF(A30=1,$B$10,H29)) -> 0 | G30: =IF(A30>$B$17,0,CHOOSE($B$18,MIN(F30,$B$10/Inputs!$B$85),F30*Inputs!$B$86,IFERROR($B$10*B30/SUM($B$25:$B$34),0))) -> 0 | H30: =F30-G30 -> 0 | I30: =IF(A30=$B$17,Inputs!$B$87*H30,0) -> 0 | J30: =IF(A30=$B$17,H30-I30,0) -> 0 | K30: =E30-G30-J30 -> 0 | L30: =MAX(0,K30)*$B$19 -> 0 | N30: =E30+I30 -> 0 | O30: =E30-L30+I30 -> 0 | P30: =1/(1+$B$20)^A30 -> 0.56447393 | Q30: =O30*P30 -> 0 | R30: =R29+O30 -> 3.9873084 | S30: =IF(AND(R29<0,R30>=0),(A30-1)+(-R29)/O30,"")
A31: 7 | B31: ='Cash flow'!C11 -> 0 | C31: =B31*Economics!$B$19/10000000 -> 0 | D31: =B31*$B$16/10000000 -> 0 | E31: =C31-D31 -> 0 | F31: =IF(A31>$B$17,0,IF(A31=1,$B$10,H30)) -> 0 | G31: =IF(A31>$B$17,0,CHOOSE($B$18,MIN(F31,$B$10/Inputs!$B$85),F31*Inputs!$B$86,IFERROR($B$10*B31/SUM($B$25:$B$34),0))) -> 0 | H31: =F31-G31 -> 0 | I31: =IF(A31=$B$17,Inputs!$B$87*H31,0) -> 0 | J31: =IF(A31=$B$17,H31-I31,0) -> 0 | K31: =E31-G31-J31 -> 0 | L31: =MAX(0,K31)*$B$19 -> 0 | N31: =E31+I31 -> 0 | O31: =E31-L31+I31 -> 0 | P31: =1/(1+$B$20)^A31 -> 0.51315812 | Q31: =O31*P31 -> 0 | R31: =R30+O31 -> 3.9873084 | S31: =IF(AND(R30<0,R31>=0),(A31-1)+(-R30)/O31,"")
A32: 8 | B32: ='Cash flow'!C12 -> 0 | C32: =B32*Economics!$B$19/10000000 -> 0 | D32: =B32*$B$16/10000000 -> 0 | E32: =C32-D32 -> 0 | F32: =IF(A32>$B$17,0,IF(A32=1,$B$10,H31)) -> 0 | G32: =IF(A32>$B$17,0,CHOOSE($B$18,MIN(F32,$B$10/Inputs!$B$85),F32*Inputs!$B$86,IFERROR($B$10*B32/SUM($B$25:$B$34),0))) -> 0 | H32: =F32-G32 -> 0 | I32: =IF(A32=$B$17,Inputs!$B$87*H32,0) -> 0 | J32: =IF(A32=$B$17,H32-I32,0) -> 0 | K32: =E32-G32-J32 -> 0 | L32: =MAX(0,K32)*$B$19 -> 0 | N32: =E32+I32 -> 0 | O32: =E32-L32+I32 -> 0 | P32: =1/(1+$B$20)^A32 -> 0.46650738 | Q32: =O32*P32 -> 0 | R32: =R31+O32 -> 3.9873084 | S32: =IF(AND(R31<0,R32>=0),(A32-1)+(-R31)/O32,"")
A33: 9 | B33: ='Cash flow'!C13 -> 0 | C33: =B33*Economics!$B$19/10000000 -> 0 | D33: =B33*$B$16/10000000 -> 0 | E33: =C33-D33 -> 0 | F33: =IF(A33>$B$17,0,IF(A33=1,$B$10,H32)) -> 0 | G33: =IF(A33>$B$17,0,CHOOSE($B$18,MIN(F33,$B$10/Inputs!$B$85),F33*Inputs!$B$86,IFERROR($B$10*B33/SUM($B$25:$B$34),0))) -> 0 | H33: =F33-G33 -> 0 | I33: =IF(A33=$B$17,Inputs!$B$87*H33,0) -> 0 | J33: =IF(A33=$B$17,H33-I33,0) -> 0 | K33: =E33-G33-J33 -> 0 | L33: =MAX(0,K33)*$B$19 -> 0 | N33: =E33+I33 -> 0 | O33: =E33-L33+I33 -> 0 | P33: =1/(1+$B$20)^A33 -> 0.42409762 | Q33: =O33*P33 -> 0 | R33: =R32+O33 -> 3.9873084 | S33: =IF(AND(R32<0,R33>=0),(A33-1)+(-R32)/O33,"")
A34: 10 | B34: ='Cash flow'!C14 -> 0 | C34: =B34*Economics!$B$19/10000000 -> 0 | D34: =B34*$B$16/10000000 -> 0 | E34: =C34-D34 -> 0 | F34: =IF(A34>$B$17,0,IF(A34=1,$B$10,H33)) -> 0 | G34: =IF(A34>$B$17,0,CHOOSE($B$18,MIN(F34,$B$10/Inputs!$B$85),F34*Inputs!$B$86,IFERROR($B$10*B34/SUM($B$25:$B$34),0))) -> 0 | H34: =F34-G34 -> 0 | I34: =IF(A34=$B$17,Inputs!$B$87*H34,0) -> 0 | J34: =IF(A34=$B$17,H34-I34,0) -> 0 | K34: =E34-G34-J34 -> 0 | L34: =MAX(0,K34)*$B$19 -> 0 | N34: =E34+I34 -> 0 | O34: =E34-L34+I34 -> 0 | P34: =1/(1+$B$20)^A34 -> 0.38554329 | Q34: =O34*P34 -> 0 | R34: =R33+O34 -> 3.9873084 | S34: =IF(AND(R33<0,R34>=0),(A34-1)+(-R33)/O34,"")
A35: Total | B35: =SUM(B24:B34) -> 1693720 | C35: =SUM(C24:C34) -> 372.6184 | D35: =SUM(D24:D34) -> 336.11052 | E35: =SUM(E24:E34) -> 36.507876 | G35: =SUM(G24:G34) -> 11 | I35: =SUM(I24:I34) -> 5.5 | J35: =SUM(J24:J34) -> 5.5 | K35: =SUM(K24:K34) -> 20.007876 | L35: =SUM(L24:L34) -> 6.0205678 | M35: =SUM(M24:M34) -> 32 | N35: =SUM(N24:N34) -> 10.007876 | O35: =SUM(O24:O34) -> 3.9873084 | Q35: =SUM(Q24:Q34) -> -3.5803276
A36: Tax is charged on EBITDA less depreciation and any loss on selling the equipment, with no carry-forward of losses. Units of production spreads the cost over tonnes mined and leaves no book value at closure.
A38: C. Project value
A39: Item | B39: Value | C39: Unit | D39: What it means
A40: Net present value, post-tax | B40: =SUM(Q24:Q34) -> -3.5803276 | C40: ₹ crore | D40: Sum of discounted post-tax cash flows, including the year-0 capital.
A41: Check: Excel NPV function | B41: =NPV(B20,O25:O34)+O24 -> -3.5803276 | C41: ₹ crore | D41: Must equal the line above.
A42: Net present value, pre-tax, explicit capital | B42: =SUMPRODUCT(N24:N34,P24:P34) -> 1.4104261 | C42: ₹ crore | D42: Same cash flows before tax.
A43: Net present value, pre-tax, Cash flow sheet | B43: ='Cash flow'!B19 -> 9.9382192 | C43: ₹ crore | D43: Ownership cost left inside the hourly rates and no equipment capital. The two pre-tax figures differ only in how equipment is treated.
A44: Internal rate of return, post-tax | B44: =IFERROR(IRR(O24:O34),"n/a") -> 0.047937961 | C44: % | D44: Discount rate at which the NPV is zero.
A45: Internal rate of return, pre-tax | B45: =IFERROR(IRR(N24:N34),"n/a") -> 0.12052084 | C45: %
A46: Payback period, post-tax | B46: =IF(COUNT(S25:S34)=0,"Not recovered",MIN(S25:S34)) -> 3.5879009 | C46: years | D46: Time for cumulative post-tax cash flow to turn positive (undiscounted, even cash flow within a year).
A47: Profitability index | B47: =IFERROR(SUM(Q25:Q34)/B12,0) -> 0.88811476 | C47: ratio | D47: PV of future cash flows ÷ capital. Above 1 creates value.
A48: Total tax paid | B48: =L35 -> 6.0205678 | C48: ₹ crore
A49: PV of the depreciation tax shield | B49: =SUMPRODUCT(G25:G34,P25:P34)*B19 -> 2.1792825 | C49: ₹ crore | D49: Tax saved because depreciation is deductible, discounted to today.

Sheet Summary
A1: Summary — the answers on one page
A2: All values are pulled from the other sheets. Do not type here.
A4: Result | B4: Value | C4: Unit | D4: How to say it in a viva
A5: Reserve
A6: Coal in place | B6: =Reserve!$B$29/1000000 -> 2.205 | C6: million t | D6: The pit holds this much coal before losses.
A7: Recoverable coal, economic blocks | B7: =Reserve!$B$39/1000000 -> 1.69372 | C7: million t | D7: What we can actually mine at a profit.
A8: Overall stripping ratio, all blocks | B8: =Reserve!$B$31 -> 2.7709751 | C8: m³/t | D8: Cubic metres of overburden to remove per tonne of coal.
A9: Economic blocks | B9: =Reserve!$B$35 -> 16 | C9: of 20 | D9: Blocks whose stripping ratio is below the break-even.
A10: Stripping ratio, economic blocks | B10: =Reserve!$B$38 -> 2.9310858 | C10: m³/t | D10: The ratio we actually plan to mine at.
A11: Mine life | B11: =Reserve!$B$40 -> 3.38744 | C11: years | D11: Recoverable coal ÷ yearly target.
A12: Fleet
A13: Excavators required | B13: =Fleet!$B$31 -> 2 | C13: machines | D13: Hours needed ÷ hours per machine, rounded up.
A14: Dumpers required | B14: =Fleet!$B$32 -> 7 | C14: machines | D14: Same method; depends on haul distance and payload.
A15: Economics
A16: Overburden removal cost | B16: =Economics!$B$9 -> 113.56092 | C16: ₹/BCM | D16: Drill-blast + excavation + haulage.
A17: Coal winning cost (excl. overburden) | B17: =Economics!$B$17 -> 1722.2159 | C17: ₹/t | D17: Everything to produce a tonne except stripping.
A18: Break-even stripping ratio | B18: =Economics!$B$21 -> 4.2072933 | C18: m³/t | D18: (Price − coal cost) ÷ overburden cost. The most you can afford to strip.
A19: All-in cost per tonne | B19: =Economics!$B$25 -> 2055.0727 | C19: ₹/t | D19: Coal cost + stripping ratio × overburden cost.
A20: Coal selling price | B20: =Economics!$B$19 -> 2200 | C20: ₹/t | D20: Assumed price.
A21: Profit per tonne | B21: =Economics!$B$26 -> 144.9273 | C21: ₹/t | D21: Price − all-in cost, before tax.
A22: Annual profit before tax | B22: =Economics!$B$31 -> 7.246365 | C22: ₹ crore | D22: Profit per tonne × yearly production.
A23: Net present value (NPV), pre-tax | B23: =Economics!$B$34 -> 9.9382192 | C23: ₹ crore | D23: Ownership cost sits inside the hourly rates. Post-tax NPV is under Finance.
A24: Verdict | B24: =Economics!$B$23 -> Viable on average | D24: Average stripping ratio vs break-even.
A26: Geostatistics
A27: Kriged coal seam thickness at the target point | B27: =Geostatistics!B73 -> 8.3934294 | C27: m | D27: Ordinary kriging of trend residuals at the point set on Inputs.
A28: 95 % confidence interval, ± | B28: =Geostatistics!B76 -> 0.70141366 | C28: m | D28: Kriging standard deviation × 1.96.
A29: Relative kriging error | B29: =Geostatistics!B77 -> 0.083566993 | C29: % | D29: Smaller means the point is well supported by nearby boreholes.
A30: Pit design
A31: Overall slope, deepest wall | B31: ='Pit design'!B43 -> 43.136306 | C31: degrees | D31: From bench height, face angle and berm width.
A32: Slope-wedge overburden | B32: ='Pit design'!B32/1000000 -> 1.076129 | C32: million BCM | D32: Wall rock that no borehole shows.
A33: Stripping ratio including pit slopes | B33: ='Pit design'!B37 -> 2.9310858 | C33: m³/t | D33: The ratio actually used for fleet and cost.
A34: Planar-failure factor of safety | B34: ='Pit design'!B52 -> 1.3391792 | C34: ratio | D34: Resisting ÷ driving force on the failure plane.
A35: Slope stability verdict | B35: ='Pit design'!B54 -> Meets target | D35: Against the target factor of safety on Inputs.
A36: Mine planning
A37: Taylor optimum production rate | B37: ='Mine planning'!B8 -> 0.23474763 | C37: million t/yr | D37: Empirical rule: a sense-check on the target.
A38: Target ÷ Taylor optimum | B38: ='Mine planning'!B13 -> 2.129947 | C38: ratio | D38: Above 1.33 is faster than the Taylor range.
A39: Effective cut-off stripping ratio | B39: ='Mine planning'!B30 -> 3.6227583 | C39: m³/t | D39: Break-even less the pit-slope burden.
A40: Blocks passing the effective cut-off | B40: ='Mine planning'!B32 -> 15 | C40: of 20 | D40: Compare with economic blocks above.
A41: Quality and statutory levies
A42: Run-of-mine ash | B42: ='Quality and royalty'!B19 -> 44.8 | C42: % | D42: From the float-and-sink data.
A43: Actual yield at the target ash | B43: ='Quality and royalty'!B26 -> 59.28 | C43: % | D43: Theoretical yield × organic efficiency.
A44: Benefit of washing over selling raw | B44: ='Quality and royalty'!B38 -> 139.76 | C44: ₹/t ROM | D44: Negative means sell raw coal.
A45: Statutory levies used in the model | B45: ='Quality and royalty'!B53 -> 900 | C45: ₹/t | D45: Royalty + DMF + NMET + other, or the flat placeholder.
A46: Safety
A47: Predicted ground vibration (PPV) | B47: =Safety!B24 -> 2.8345128 | C47: mm/s | D47: Scaled-distance law at the nearest structure.
A48: Permissible PPV (DGMS) | B48: =Safety!B25 -> 10 | C48: mm/s | D48: For the structure type and frequency band chosen.
A49: Vibration status | B49: =Safety!B26 -> Within limit
A50: Safe distance at this charge | B50: =Safety!B28 -> 136.43326 | C50: m | D50: Closest a structure can be at the permissible PPV.
A51: Finance
A52: Total capital at year 0 | B52: =Finance!B12 -> 32 | C52: ₹ crore | D52: Equipment plus non-equipment capital.
A53: NPV, post-tax | B53: =Finance!B40 -> -3.5803276 | C53: ₹ crore | D53: After depreciation and tax; equipment capital explicit.
A54: IRR, post-tax | B54: =Finance!B44 -> 0.047937961 | C54: % | D54: Rate at which the post-tax NPV is zero.
A55: Payback period, post-tax | B55: =Finance!B46 -> 3.5879009 | C55: years | D55: Undiscounted.
A56: Largest NPV driver | B56: =#REF! -> #REF! | D56: From the Sensitivity tornado.
A58: Questions to practise answering out loud
A59: • Why is the stripping ratio the key number in opencast planning?
A60: • How did you decide which blocks to mine and which to leave?
A61: • What is the break-even stripping ratio and how did you calculate it?
A62: • How many dumpers per excavator did you need, and why that number?
A63: • Which input moves the NPV the most? Test coal price, haul distance and recovery.
A64: • What does your model ignore, and how would real planning software handle it?
A65: • How does a pit slope add to the stripping ratio, and what limits how steep the wall can be?
A66: • What does the kriging variance tell you that a polygon estimate does not?
A67: • Why is depreciation deducted for tax but not from cash flow?
A68: • How are royalty, DMF and NMET calculated, and how much of the coal price do they take?
A69: • How do you decide whether to wash coal, and what is organic efficiency?
A70: • How do you keep ground vibration within the DGMS limit at a nearby village?
